Workbook

Sheet Instructions
B2: Meridian Consulting Group
B3: Simulated Sales History & Pipeline Dataset — for Dashboard Analysis Exercise
B5: Business Context
B6: Company | C6: Meridian Consulting Group (fictitious) — a mid-size, project-based management & technology consulting firm operating across 4 regions and 8 service lines.
B7: Business model | C7: Project-based engagements (not subscriptions). "Churn" here means a client that has NOT come back for a repeat engagement within a reasonable window after their last project ended — see the Clients sheet's Client_Status column.
B8: Data scope | C8: 760 historical opportunities closed over the last 3 years (Won/Lost), plus 150 currently OPEN pipeline opportunities created over the last 2 years and not yet closed.
B10: Your Task
B11: Objective | C11: Build a dashboard from this data (Excel, Power BI, Tableau, or similar) and produce a short, data-backed recommendation covering the three questions below.
B12: Q1 — Win Rate | C12: What is our win rate overall and by segment (region, service line, lead source, sales rep)? What should our strategy be to improve win %?
B13: Q2 — Churn | C13: What share of clients who have won business with us come back for repeat engagements vs. go quiet ("churn")? What should we do to reduce churn / increase repeat business?
B14: Q3 — Pipeline Generation | C14: How healthy is our open pipeline (volume, value, weighted value, coverage by stage)? What should we do to generate more/better pipeline?
B16: Important Methodology Note
B17: How this data was built | C17: This dataset is randomly simulated for training purposes. Category assignments (region, service line, lead source, rep) were drawn independently at random — no segment was deliberately scripted to win more, churn more, or perform differently. Real operational data may or may not show similar patterns.
B18: Implication for analysis | C18: Any differences you observe between segments (e.g. one lead source appears to convert better) may be genuine signal OR sampling noise given the sample sizes involved. Good analysis should sanity-check apparent patterns (sample size, consistency over time) before building a strategy recommendation on them — that critical-thinking step is itself part of the exercise.
B20: Workbook Contents
B21: Instructions | C21: This sheet.
B22: Closed_Deals | C22: 760 historical opportunities (Won/Lost) closed over the last 3 years. One row per opportunity. Core table for win-rate and revenue analysis.
B23: Open_Pipeline | C23: 150 currently open opportunities created over the last 2 years, not yet closed. Core table for pipeline health / generation analysis.
B24: Clients | C24: One row per client (260), with formulas rolling up their closed-deal and open-pipeline history, including a computed Client_Status (Active / At Risk / Churned / No Won Business) for churn analysis.
B25: Sales_Reps | C25: One row per sales rep (24), with formulas rolling up their win rate, revenue, average sales cycle, and open pipeline.
B26: KPI_Summary | C26: Headline KPIs and pre-built breakdown tables (by service line, region, lead source, pipeline stage, loss reason, client status) — a starting point for your dashboard, all driven by formulas so they recalculate if the underlying data changes.
B28: Data Dictionary — Closed_Deals
B29: Deal_ID | C29: Unique opportunity identifier.
B30: Client_ID / Client_Name / Industry / Region | C30: The client and its attributes.
B31: Service_Line | C31: Which of the 8 consulting service lines the opportunity was for.
B32: Lead_Source | C32: How the opportunity originated (referral, RFP, outbound, etc.).
B33: Sales_Rep_ID / Sales_Rep_Name | C33: Owning sales rep.
B34: Created_Date / Closed_Date | C34: When the opportunity was opened and when it closed (Won or Lost).
B35: Sales_Cycle_Days | C35: Formula: Closed_Date − Created_Date.
B36: Deal_Value_USD | C36: Total contract value proposed.
B37: Outcome | C37: Won or Lost.
B38: Loss_Reason | C38: Populated only when Outcome = Lost.
B39: Project_Start_Date / Project_Duration_Months | C39: Populated only when Outcome = Won.
B40: Project_End_Date | C40: Formula: Project_Start_Date + Project_Duration_Months (via EDATE); used by the Clients sheet to detect repeat business / churn.
B42: Data Dictionary — Open_Pipeline
B43: Opportunity_ID | C43: Unique open-opportunity identifier.
B44: Client/Industry/Region/Service_Line/Lead_Source/Sales_Rep | C44: Same meaning as Closed_Deals.
B45: Created_Date | C45: When the opportunity was opened (still open today).
B46: Stage | C46: Current pipeline stage: Prospecting, Qualification, Proposal/Solutioning, Negotiation.
B47: Stage_Probability | C47: Estimated probability of winning, based on stage.
B48: Deal_Value_USD | C48: Proposed contract value.
B49: Weighted_Pipeline_Value | C49: Formula: Deal_Value_USD × Stage_Probability.
B50: Expected_Close_Date | C50: Forecast close date.
B51: Age_In_Pipeline_Days | C51: Formula: today − Created_Date.
B52: Days_To_Expected_Close | C52: Formula: Expected_Close_Date − today.

Sheet Closed_Deals
A1: Deal_ID | B1: Client_ID | C1: Client_Name | D1: Industry | E1: Region | F1: Service_Line | G1: Lead_Source | H1: Sales_Rep_ID | I1: Sales_Rep_Name | J1: Created_Date | K1: Closed_Date | L1: Sales_Cycle_Days | M1: Deal_Value_USD | N1: Outcome | O1: Loss_Reason | P1: Project_Start_Date | Q1: Project_Duration_Months | R1: Project_End_Date
A2: CD-00001 | B2: CLI-0086 | C2: Anchor Motors | D2: Healthcare | E2: LATAM | F2: Risk & Compliance | G2: Outbound Prospecting | H2: REP-016 | I2: Nikolai Khan | J2: 45124 | K2: 45186 | L2: =K2-J2 -> 62 | M2: 48260.82 | N2: Lost | O2: Budget Cut
A3: CD-00002 | B3: CLI-0138 | C3: Apex Materials | D3: Manufacturing | E3: North America | F3: Data & Analytics | G3: Partner Referral | H3: REP-009 | I3: Ahmed Petrov | J3: 45121 | K3: 45192 | L3: =K3-J3 -> 71 | M3: 103481.4 | N3: Lost | O3: Lost to Competitor
A4: CD-00003 | B4: CLI-0174 | C4: Granite Dynamics | D4: Technology | E4: EMEA | F4: Technology Consulting | G4: Inbound Marketing | H4: REP-009 | I4: Ahmed Petrov | J4: 45101 | K4: 45200 | L4: =K4-J4 -> 99 | M4: 178890.57 | N4: Lost | O4: Scope Mismatch
A5: CD-00004 | B5: CLI-0132 | C5: Blue Telecom | D5: Manufacturing | E5: North America | F5: Data & Analytics | G5: Inbound Marketing | H5: REP-004 | I5: Wei Müller | J5: 45126 | K5: 45207 | L5: =K5-J5 -> 81 | M5: 139590.37 | N5: Lost | O5: Went with In-house Team
A6: CD-00005 | B6: CLI-0229 | C6: Harbor Foods | D6: Manufacturing | E6: North America | F6: HR & Change Management | G6: Inbound Marketing | H6: REP-014 | I6: Miguel Hassan | J6: 45177 | K6: 45212 | L6: =K6-J6 -> 35 | M6: 36018.82 | N6: Won | P6: 45220 | Q6: 1 | R6: =EDATE(P6,Q6) -> 45251
A7: CD-00006 | B7: CLI-0023 | C7: Falcon Networks | D7: Public Sector | E7: LATAM | F7: Strategy Consulting | G7: RFP/Tender | H7: REP-005 | I7: Grace Lee | J7: 45112 | K7: 45222 | L7: =K7-J7 -> 110 | M7: 63541.54 | N7: Won | P7: 45235 | Q7: 2 | R7: =EDATE(P7,Q7) -> 45296
A8: CD-00007 | B8: CLI-0247 | C8: Pioneer Retail | D8: Manufacturing | E8: North America | F8: Digital Transformation | G8: Event/Conference | H8: REP-023 | I8: Daniel Larsen | J8: 45142 | K8: 45222 | L8: =K8-J8 -> 80 | M8: 82458.1 | N8: Lost | O8: No Decision/Timing
A9: CD-00008 | B9: CLI-0162 | C9: Silver Bank | D9: Telecom | E9: LATAM | F9: Strategy Consulting | G9: Inbound Marketing | H9: REP-024 | I9: Lucas Mansour | J9: 45151 | K9: 45234 | L9: =K9-J9 -> 83 | M9: 125009.81 | N9: Lost | O9: Budget Cut
A10: CD-00009 | B10: CLI-0060 | C10: Anchor Industries | D10: Manufacturing | E10: North America | F10: Operations Consulting | G10: Inbound Marketing | H10: REP-016 | I10: Nikolai Khan | J10: 45128 | K10: 45237 | L10: =K10-J10 -> 109 | M10: 185405.11 | N10: Lost | O10: Went with In-house Team
A11: CD-00010 | B11: CLI-0132 | C11: Blue Telecom | D11: Manufacturing | E11: North America | F11: Operations Consulting | G11: RFP/Tender | H11: REP-024 | I11: Lucas Mansour | J11: 45193 | K11: 45241 | L11: =K11-J11 -> 48 | M11: 145078.8 | N11: Lost | O11: Went with In-house Team
A12: CD-00011 | B12: CLI-0080 | C12: Anchor Dynamics | D12: Telecom | E12: APAC | F12: Strategy Consulting | G12: Outbound Prospecting | H12: REP-005 | I12: Grace Lee | J12: 45156 | K12: 45244 | L12: =K12-J12 -> 88 | M12: 128428.3 | N12: Lost | O12: Scope Mismatch
A13: CD-00012 | B13: CLI-0187 | C13: Highland Capital | D13: Telecom | E13: LATAM | F13: Digital Transformation | G13: Inbound Marketing | H13: REP-008 | I13: Ingrid Johnson | J13: 45168 | K13: 45246 | L13: =K13-J13 -> 78 | M13: 24214.25 | N13: Lost | O13: Went with In-house Team
A14: CD-00013 | B14: CLI-0027 | C14: Crown Partners | D14: Manufacturing | E14: LATAM | F14: HR & Change Management | G14: Outbound Prospecting | H14: REP-018 | I14: Sarah Garcia | J14: 45187 | K14: 45251 | L14: =K14-J14 -> 64 | M14: 26961.43 | N14: Won | P14: 45269 | Q14: 3 | R14: =EDATE(P14,Q14) -> 45360
A15: CD-00014 | B15: CLI-0016 | C15: Silver Enterprises | D15: Manufacturing | E15: LATAM | F15: Strategy Consulting | G15: Existing Client Upsell | H15: REP-007 | I15: Peter Khan | J15: 45167 | K15: 45253 | L15: =K15-J15 -> 86 | M15: 92364.93 | N15: Lost | O15: No Decision/Timing
A16: CD-00015 | B16: CLI-0027 | C16: Crown Partners | D16: Manufacturing | E16: LATAM | F16: Data & Analytics | G16: Inbound Marketing | H16: REP-010 | I16: Laura Sharma | J16: 45165 | K16: 45253 | L16: =K16-J16 -> 88 | M16: 76838.63 | N16: Lost | O16: Budget Cut
A17: CD-00016 | B17: CLI-0187 | C17: Highland Capital | D17: Telecom | E17: LATAM | F17: Financial Advisory | G17: Referral | H17: REP-019 | I17: Lucas Silva | J17: 45144 | K17: 45258 | L17: =K17-J17 -> 114 | M17: 374906.37 | N17: Won | P17: 45267 | Q17: 3 | R17: =EDATE(P17,Q17) -> 45358
A18: CD-00017 | B18: CLI-0111 | C18: Vertex Partners | D18: Telecom | E18: North America | F18: Data & Analytics | G18: Existing Client Upsell | H18: REP-020 | I18: Omar Lee | J18: 45206 | K18: 45260 | L18: =K18-J18 -> 54 | M18: 68804.87 | N18: Won | P18: 45273 | Q18: 4 | R18: =EDATE(P18,Q18) -> 45395
A19: CD-00018 | B19: CLI-0197 | C19: Falcon Solutions | D19: Financial Services | E19: EMEA | F19: Digital Transformation | G19: Existing Client Upsell | H19: REP-021 | I19: Daniel Lee | J19: 45183 | K19: 45264 | L19: =K19-J19 -> 81 | M19: 173800.45 | N19: Won | P19: 45266 | Q19: 4 | R19: =EDATE(P19,Q19) -> 45388
A20: CD-00019 | B20: CLI-0109 | C20: Sterling Dynamics | D20: Energy & Utilities | E20: LATAM | F20: Risk & Compliance | G20: Existing Client Upsell | H20: REP-021 | I20: Daniel Lee | J20: 45158 | K20: 45270 | L20: =K20-J20 -> 112 | M20: 102757.36 | N20: Lost | O20: Budget Cut
A21: CD-00020 | B21: CLI-0240 | C21: Meridian Telecom | D21: Financial Services | E21: LATAM | F21: Technology Consulting | G21: Partner Referral | H21: REP-003 | I21: Wei Brown | J21: 45213 | K21: 45273 | L21: =K21-J21 -> 60 | M21: 123671.38 | N21: Lost | O21: No Decision/Timing
A22: CD-00021 | B22: CLI-0244 | C22: Beacon Retail | D22: Technology | E22: APAC | F22: Digital Transformation | G22: Outbound Prospecting | H22: REP-009 | I22: Ahmed Petrov | J22: 45207 | K22: 45276 | L22: =K22-J22 -> 69 | M22: 180899.78 | N22: Lost | O22: No Decision/Timing
A23: CD-00022 | B23: CLI-0099 | C23: Highland Foods | D23: Energy & Utilities | E23: North America | F23: Financial Advisory | G23: Event/Conference | H23: REP-012 | I23: Raj Chen | J23: 45222 | K23: 45285 | L23: =K23-J23 -> 63 | M23: 46795.32 | N23: Won | P23: 45308 | Q23: 2 | R23: =EDATE(P23,Q23) -> 45368
A24: CD-00023 | B24: CLI-0197 | C24: Falcon Solutions | D24: Financial Services | E24: EMEA | F24: Operations Consulting | G24: Referral | H24: REP-019 | I24: Lucas Silva | J24: 45238 | K24: 45299 | L24: =K24-J24 -> 61 | M24: 43792.75 | N24: Won | P24: 45310 | Q24: 3 | R24: =EDATE(P24,Q24) -> 45401
A25: CD-00024 | B25: CLI-0176 | C25: Ironclad Foods | D25: Manufacturing | E25: North America | F25: Risk & Compliance | G25: RFP/Tender | H25: REP-020 | I25: Omar Lee | J25: 45219 | K25: 45301 | L25: =K25-J25 -> 82 | M25: 95571.34 | N25: Lost | O25: Price/Budget
A26: CD-00025 | B26: CLI-0151 | C26: Atlas Motors | D26: Public Sector | E26: APAC | F26: Data & Analytics | G26: Referral | H26: REP-011 | I26: Aisha Kim | J26: 45243 | K26: 45301 | L26: =K26-J26 -> 58 | M26: 91135.97 | N26: Won | P26: 45325 | Q26: 6 | R26: =EDATE(P26,Q26) -> 45507
A27: CD-00026 | B27: CLI-0249 | C27: Lakeside Motors | D27: Healthcare | E27: North America | F27: Digital Transformation | G27: RFP/Tender | H27: REP-016 | I27: Nikolai Khan | J27: 45196 | K27: 45309 | L27: =K27-J27 -> 113 | M27: 198899.81 | N27: Lost | O27: Went with In-house Team
A28: CD-00027 | B28: CLI-0047 | C28: Lakeside Technologies | D28: Healthcare | E28: LATAM | F28: Digital Transformation | G28: Event/Conference | H28: REP-013 | I28: Peter Costa | J28: 45248 | K28: 45309 | L28: =K28-J28 -> 61 | M28: 52815.33 | N28: Lost | O28: Budget Cut
A29: CD-00028 | B29: CLI-0043 | C29: Pioneer Materials | D29: Technology | E29: EMEA | F29: Risk & Compliance | G29: Event/Conference | H29: REP-016 | I29: Nikolai Khan | J29: 45217 | K29: 45318 | L29: =K29-J29 -> 101 | M29: 72010.39 | N29: Lost | O29: No Decision/Timing
A30: CD-00029 | B30: CLI-0049 | C30: Orion Dynamics | D30: Financial Services | E30: LATAM | F30: Operations Consulting | G30: Partner Referral | H30: REP-010 | I30: Laura Sharma | J30: 45297 | K30: 45319 | L30: =K30-J30 -> 22 | M30: 41047.04 | N30: Won | P30: 45329 | Q30: 2 | R30: =EDATE(P30,Q30) -> 45389
A31: CD-00030 | B31: CLI-0195 | C31: Ironclad Retail | D31: Retail & Consumer | E31: North America | F31: Operations Consulting | G31: Partner Referral | H31: REP-008 | I31: Ingrid Johnson | J31: 45255 | K31: 45319 | L31: =K31-J31 -> 64 | M31: 74489.47 | N31: Won | P31: 45339 | Q31: 5 | R31: =EDATE(P31,Q31) -> 45490
A32: CD-00031 | B32: CLI-0143 | C32: Ironclad Enterprises | D32: Public Sector | E32: APAC | F32: Risk & Compliance | G32: Existing Client Upsell | H32: REP-003 | I32: Wei Brown | J32: 45254 | K32: 45319 | L32: =K32-J32 -> 65 | M32: 86964.11 | N32: Lost | O32: Budget Cut
A33: CD-00032 | B33: CLI-0121 | C33: Granite Technologies | D33: Financial Services | E33: LATAM | F33: Data & Analytics | G33: Outbound Prospecting | H33: REP-008 | I33: Ingrid Johnson | J33: 45270 | K33: 45323 | L33: =K33-J33 -> 53 | M33: 170523.26 | N33: Lost | O33: Budget Cut
A34: CD-00033 | B34: CLI-0103 | C34: Sterling Materials | D34: Financial Services | E34: North America | F34: Risk & Compliance | G34: Existing Client Upsell | H34: REP-003 | I34: Wei Brown | J34: 45238 | K34: 45326 | L34: =K34-J34 -> 88 | M34: 101426.29 | N34: Won | P34: 45330 | Q34: 1 | R34: =EDATE(P34,Q34) -> 45359
A35: CD-00034 | B35: CLI-0223 | C35: Continental Retail | D35: Retail & Consumer | E35: North America | F35: Technology Consulting | G35: Event/Conference | H35: REP-011 | I35: Aisha Kim | J35: 45236 | K35: 45327 | L35: =K35-J35 -> 91 | M35: 225515.7 | N35: Won | P35: 45341 | Q35: 7 | R35: =EDATE(P35,Q35) -> 45554
A36: CD-00035 | B36: CLI-0069 | C36: Coastal Logistics | D36: Public Sector | E36: APAC | F36: Technology Consulting | G36: Inbound Marketing | H36: REP-017 | I36: Tom Mansour | J36: 45260 | K36: 45328 | L36: =K36-J36 -> 68 | M36: 138046.84 | N36: Won | P36: 45348 | Q36: 7 | R36: =EDATE(P36,Q36) -> 45561
A37: CD-00036 | B37: CLI-0106 | C37: Horizon Materials | D37: Healthcare | E37: LATAM | F37: Financial Advisory | G37: Event/Conference | H37: REP-008 | I37: Ingrid Johnson | J37: 45212 | K37: 45335 | L37: =K37-J37 -> 123 | M37: 85056.79 | N37: Lost | O37: Went with In-house Team
A38: CD-00037 | B38: CLI-0069 | C38: Coastal Logistics | D38: Public Sector | E38: APAC | F38: Technology Consulting | G38: Inbound Marketing | H38: REP-017 | I38: Tom Mansour | J38: 45234 | K38: 45335 | L38: =K38-J38 -> 101 | M38: 86505.77 | N38: Won | P38: 45339 | Q38: 8 | R38: =EDATE(P38,Q38) -> 45582
A39: CD-00038 | B39: CLI-0002 | C39: Crown Retail | D39: Telecom | E39: EMEA | F39: Data & Analytics | G39: Outbound Prospecting | H39: REP-011 | I39: Aisha Kim | J39: 45274 | K39: 45343 | L39: =K39-J39 -> 69 | M39: 90808.08 | N39: Lost | O39: Budget Cut
A40: CD-00039 | B40: CLI-0124 | C40: Horizon Systems | D40: Manufacturing | E40: North America | F40: Financial Advisory | G40: RFP/Tender | H40: REP-022 | I40: Nikolai Sato | J40: 45280 | K40: 45344 | L40: =K40-J40 -> 64 | M40: 39018.82 | N40: Lost | O40: Scope Mismatch
A41: CD-00040 | B41: CLI-0125 | C41: Anchor Partners | D41: Financial Services | E41: LATAM | F41: HR & Change Management | G41: Partner Referral | H41: REP-005 | I41: Grace Lee | J41: 45262 | K41: 45345 | L41: =K41-J41 -> 83 | M41: 93703.96 | N41: Won | P41: 45349 | Q41: 3 | R41: =EDATE(P41,Q41) -> 45439
A42: CD-00041 | B42: CLI-0169 | C42: Continental Foods | D42: Technology | E42: APAC | F42: Financial Advisory | G42: Event/Conference | H42: REP-002 | I42: Aisha Sato | J42: 45296 | K42: 45350 | L42: =K42-J42 -> 54 | M42: 154863.47 | N42: Lost | O42: Went with In-house Team
A43: CD-00042 | B43: CLI-0111 | C43: Vertex Partners | D43: Telecom | E43: North America | F43: Data & Analytics | G43: Existing Client Upsell | H43: REP-015 | I43: Yuki Garcia | J43: 45212 | K43: 45350 | L43: =K43-J43 -> 138 | M43: 401197.37 | N43: Won | P43: 45358 | Q43: 2 | R43: =EDATE(P43,Q43) -> 45419
A44: CD-00043 | B44: CLI-0248 | C44: Horizon Partners | D44: Energy & Utilities | E44: North America | F44: Strategy Consulting | G44: Event/Conference | H44: REP-010 | I44: Laura Sharma | J44: 45262 | K44: 45354 | L44: =K44-J44 -> 92 | M44: 211887.66 | N44: Lost | O44: Price/Budget
A45: CD-00044 | B45: CLI-0113 | C45: Metro Materials | D45: Telecom | E45: LATAM | F45: Digital Transformation | G45: Existing Client Upsell | H45: REP-005 | I45: Grace Lee | J45: 45291 | K45: 45357 | L45: =K45-J45 -> 66 | M45: 113498.02 | N45: Lost | O45: No Decision/Timing
A46: CD-00045 | B46: CLI-0162 | C46: Silver Bank | D46: Telecom | E46: LATAM | F46: Strategy Consulting | G46: Inbound Marketing | H46: REP-021 | I46: Daniel Lee | J46: 45305 | K46: 45363 | L46: =K46-J46 -> 58 | M46: 104282.91 | N46: Won | P46: 45387 | Q46: 4 | R46: =EDATE(P46,Q46) -> 45509
A47: CD-00046 | B47: CLI-0211 | C47: Horizon Bank | D47: Energy & Utilities | E47: LATAM | F47: Risk & Compliance | G47: Outbound Prospecting | H47: REP-021 | I47: Daniel Lee | J47: 45278 | K47: 45363 | L47: =K47-J47 -> 85 | M47: 22811.49 | N47: Won | P47: 45387 | Q47: 2 | R47: =EDATE(P47,Q47) -> 45448
A48: CD-00047 | B48: CLI-0230 | C48: Union Networks | D48: Healthcare | E48: LATAM | F48: Operations Consulting | G48: Outbound Prospecting | H48: REP-007 | I48: Peter Khan | J48: 45267 | K48: 45363 | L48: =K48-J48 -> 96 | M48: 56858.3 | N48: Lost | O48: Scope Mismatch
A49: CD-00048 | B49: CLI-0087 | C49: Meridian Health | D49: Energy & Utilities | E49: APAC | F49: Operations Consulting | G49: Inbound Marketing | H49: REP-021 | I49: Daniel Lee | J49: 45289 | K49: 45363 | L49: =K49-J49 -> 74 | M49: 64729.4 | N49: Won | P49: 45366 | Q49: 5 | R49: =EDATE(P49,Q49) -> 45519
A50: CD-00049 | B50: CLI-0158 | C50: Blue Technologies | D50: Manufacturing | E50: LATAM | F50: Digital Transformation | G50: Outbound Prospecting | H50: REP-002 | I50: Aisha Sato | J50: 45270 | K50: 45366 | L50: =K50-J50 -> 96 | M50: 89744.97 | N50: Lost | O50: Went with In-house Team
A51: CD-00050 | B51: CLI-0232 | C51: Beacon Bank | D51: Healthcare | E51: EMEA | F51: Financial Advisory | G51: Outbound Prospecting | H51: REP-001 | I51: Wei Mansour | J51: 45310 | K51: 45367 | L51: =K51-J51 -> 57 | M51: 89737.66 | N51: Won | P51: 45380 | Q51: 2 | R51: =EDATE(P51,Q51) -> 45441
A52: CD-00051 | B52: CLI-0202 | C52: Atlas Solutions | D52: Financial Services | E52: North America | F52: Financial Advisory | G52: Existing Client Upsell | H52: REP-023 | I52: Daniel Larsen | J52: 45305 | K52: 45367 | L52: =K52-J52 -> 62 | M52: 134518.35 | N52: Won | P52: 45389 | Q52: 3 | R52: =EDATE(P52,Q52) -> 45480
A53: CD-00052 | B53: CLI-0234 | C53: Anchor Group | D53: Public Sector | E53: North America | F53: Digital Transformation | G53: Partner Referral | H53: REP-019 | I53: Lucas Silva | J53: 45242 | K53: 45370 | L53: =K53-J53 -> 128 | M53: 146441.22 | N53: Lost | O53: Budget Cut
A54: CD-00053 | B54: CLI-0195 | C54: Ironclad Retail | D54: Retail & Consumer | E54: North America | F54: Digital Transformation | G54: Existing Client Upsell | H54: REP-013 | I54: Peter Costa | J54: 45253 | K54: 45371 | L54: =K54-J54 -> 118 | M54: 134375.41 | N54: Won | P54: 45376 | Q54: 4 | R54: =EDATE(P54,Q54) -> 45498
A55: CD-00054 | B55: CLI-0071 | C55: Bridgeway Enterprises | D55: Financial Services | E55: APAC | F55: Digital Transformation | G55: Inbound Marketing | H55: REP-023 | I55: Daniel Larsen | J55: 45271 | K55: 45372 | L55: =K55-J55 -> 101 | M55: 156917.43 | N55: Won | P55: 45393 | Q55: 9 | R55: =EDATE(P55,Q55) -> 45668
A56: CD-00055 | B56: CLI-0137 | C56: Meridian Capital | D56: Technology | E56: LATAM | F56: Financial Advisory | G56: Inbound Marketing | H56: REP-024 | I56: Lucas Mansour | J56: 45291 | K56: 45372 | L56: =K56-J56 -> 81 | M56: 129653.96 | N56: Won | P56: 45374 | Q56: 2 | R56: =EDATE(P56,Q56) -> 45435
A57: CD-00056 | B57: CLI-0118 | C57: Blue Capital | D57: Energy & Utilities | E57: LATAM | F57: Risk & Compliance | G57: RFP/Tender | H57: REP-013 | I57: Peter Costa | J57: 45293 | K57: 45374 | L57: =K57-J57 -> 81 | M57: 98377.57 | N57: Lost | O57: Scope Mismatch
A58: CD-00057 | B58: CLI-0051 | C58: Granite Networks | D58: Financial Services | E58: LATAM | F58: Financial Advisory | G58: Existing Client Upsell | H58: REP-024 | I58: Lucas Mansour | J58: 45320 | K58: 45375 | L58: =K58-J58 -> 55 | M58: 88217.73 | N58: Won | P58: 45377 | Q58: 3 | R58: =EDATE(P58,Q58) -> 45469
A59: CD-00058 | B59: CLI-0128 | C59: Horizon Group | D59: Energy & Utilities | E59: LATAM | F59: Digital Transformation | G59: Partner Referral | H59: REP-024 | I59: Lucas Mansour | J59: 45285 | K59: 45388 | L59: =K59-J59 -> 103 | M59: 80488.69 | N59: Won | P59: 45392 | Q59: 7 | R59: =EDATE(P59,Q59) -> 45606
A60: CD-00059 | B60: CLI-0173 | C60: Silver Motors | D60: Retail & Consumer | E60: APAC | F60: Financial Advisory | G60: Inbound Marketing | H60: REP-023 | I60: Daniel Larsen | J60: 45313 | K60: 45389 | L60: =K60-J60 -> 76 | M60: 146175.17 | N60: Lost | O60: Price/Budget
A61: CD-00060 | B61: CLI-0049 | C61: Orion Dynamics | D61: Financial Services | E61: LATAM | F61: Financial Advisory | G61: Inbound Marketing | H61: REP-007 | I61: Peter Khan | J61: 45347 | K61: 45391 | L61: =K61-J61 -> 44 | M61: 38755.03 | N61: Lost | O61: Scope Mismatch
A62: CD-00061 | B62: CLI-0053 | C62: Beacon Partners | D62: Retail & Consumer | E62: APAC | F62: Strategy Consulting | G62: RFP/Tender | H62: REP-010 | I62: Laura Sharma | J62: 45294 | K62: 45393 | L62: =K62-J62 -> 99 | M62: 282632.76 | N62: Lost | O62: No Decision/Timing
A63: CD-00062 | B63: CLI-0181 | C63: Lakeside Health | D63: Energy & Utilities | E63: LATAM | F63: Technology Consulting | G63: Outbound Prospecting | H63: REP-001 | I63: Wei Mansour | J63: 45328 | K63: 45396 | L63: =K63-J63 -> 68 | M63: 79973.24 | N63: Lost | O63: No Decision/Timing
A64: CD-00063 | B64: CLI-0050 | C64: Silver Solutions | D64: Telecom | E64: North America | F64: Technology Consulting | G64: Referral | H64: REP-022 | I64: Nikolai Sato | J64: 45352 | K64: 45399 | L64: =K64-J64 -> 47 | M64: 71334.16 | N64: Won | P64: 45422 | Q64: 6 | R64: =EDATE(P64,Q64) -> 45606
A65: CD-00064 | B65: CLI-0048 | C65: Continental Telecom | D65: Healthcare | E65: LATAM | F65: Operations Consulting | G65: Outbound Prospecting | H65: REP-019 | I65: Lucas Silva | J65: 45351 | K65: 45399 | L65: =K65-J65 -> 48 | M65: 60253.12 | N65: Won | P65: 45402 | Q65: 4 | R65: =EDATE(P65,Q65) -> 45524
A66: CD-00065 | B66: CLI-0125 | C66: Anchor Partners | D66: Financial Services | E66: LATAM | F66: Technology Consulting | G66: RFP/Tender | H66: REP-023 | I66: Daniel Larsen | J66: 45356 | K66: 45402 | L66: =K66-J66 -> 46 | M66: 139482.37 | N66: Won | P66: 45411 | Q66: 4 | R66: =EDATE(P66,Q66) -> 45533
A67: CD-00066 | B67: CLI-0102 | C67: Falcon Health | D67: Telecom | E67: LATAM | F67: Digital Transformation | G67: Outbound Prospecting | H67: REP-003 | I67: Wei Brown | J67: 45341 | K67: 45402 | L67: =K67-J67 -> 61 | M67: 136268.03 | N67: Lost | O67: Price/Budget
A68: CD-00067 | B68: CLI-0236 | C68: Continental Energy | D68: Retail & Consumer | E68: APAC | F68: Risk & Compliance | G68: RFP/Tender | H68: REP-002 | I68: Aisha Sato | J68: 45337 | K68: 45405 | L68: =K68-J68 -> 68 | M68: 83388.07 | N68: Lost | O68: Price/Budget
A69: CD-00068 | B69: CLI-0166 | C69: Horizon Motors | D69: Telecom | E69: North America | F69: Financial Advisory | G69: Event/Conference | H69: REP-004 | I69: Wei Müller | J69: 45325 | K69: 45407 | L69: =K69-J69 -> 82 | M69: 166456.85 | N69: Won | P69: 45415 | Q69: 2 | R69: =EDATE(P69,Q69) -> 45476
A70: CD-00069 | B70: CLI-0076 | C70: Bridgeway Motors | D70: Technology | E70: North America | F70: Digital Transformation | G70: Event/Conference | H70: REP-022 | I70: Nikolai Sato | J70: 45372 | K70: 45416 | L70: =K70-J70 -> 44 | M70: 60233.59 | N70: Won | P70: 45425 | Q70: 9 | R70: =EDATE(P70,Q70) -> 45701
A71: CD-00070 | B71: CLI-0189 | C71: Cedar Materials | D71: Technology | E71: LATAM | F71: Data & Analytics | G71: Event/Conference | H71: REP-010 | I71: Laura Sharma | J71: 45320 | K71: 45418 | L71: =K71-J71 -> 98 | M71: 125907.93 | N71: Lost | O71: Scope Mismatch
A72: CD-00071 | B72: CLI-0200 | C72: Crown Industries | D72: Financial Services | E72: APAC | F72: Strategy Consulting | G72: Partner Referral | H72: REP-019 | I72: Lucas Silva | J72: 45345 | K72: 45420 | L72: =K72-J72 -> 75 | M72: 92441.17 | N72: Lost | O72: Scope Mismatch
A73: CD-00072 | B73: CLI-0118 | C73: Blue Capital | D73: Energy & Utilities | E73: LATAM | F73: Technology Consulting | G73: Referral | H73: REP-011 | I73: Aisha Kim | J73: 45347 | K73: 45423 | L73: =K73-J73 -> 76 | M73: 103332.07 | N73: Lost | O73: Budget Cut
A74: CD-00073 | B74: CLI-0183 | C74: Blue Industries | D74: Technology | E74: APAC | F74: Risk & Compliance | G74: Event/Conference | H74: REP-024 | I74: Lucas Mansour | J74: 45345 | K74: 45428 | L74: =K74-J74 -> 83 | M74: 70037.56 | N74: Lost | O74: Scope Mismatch
A75: CD-00074 | B75: CLI-0203 | C75: Crown Holdings | D75: Retail & Consumer | E75: EMEA | F75: Digital Transformation | G75: Partner Referral | H75: REP-007 | I75: Peter Khan | J75: 45342 | K75: 45430 | L75: =K75-J75 -> 88 | M75: 83242.01 | N75: Lost | O75: Budget Cut
A76: CD-00075 | B76: CLI-0225 | C76: Ironclad Holdings | D76: Retail & Consumer | E76: North America | F76: Technology Consulting | G76: Event/Conference | H76: REP-015 | I76: Yuki Garcia | J76: 45362 | K76: 45431 | L76: =K76-J76 -> 69 | M76: 118361 | N76: Lost | O76: Budget Cut
A77: CD-00076 | B77: CLI-0009 | C77: Falcon Retail | D77: Energy & Utilities | E77: EMEA | F77: Risk & Compliance | G77: Partner Referral | H77: REP-020 | I77: Omar Lee | J77: 45370 | K77: 45431 | L77: =K77-J77 -> 61 | M77: 58830.83 | N77: Lost | O77: Went with In-house Team
A78: CD-00077 | B78: CLI-0148 | C78: Ironclad Dynamics | D78: Healthcare | E78: LATAM | F78: Risk & Compliance | G78: Referral | H78: REP-020 | I78: Omar Lee | J78: 45346 | K78: 45431 | L78: =K78-J78 -> 85 | M78: 86762.99 | N78: Lost | O78: Lost to Competitor
A79: CD-00078 | B79: CLI-0053 | C79: Beacon Partners | D79: Retail & Consumer | E79: APAC | F79: Risk & Compliance | G79: Existing Client Upsell | H79: REP-007 | I79: Peter Khan | J79: 45330 | K79: 45432 | L79: =K79-J79 -> 102 | M79: 54666.17 | N79: Won | P79: 45455 | Q79: 1 | R79: =EDATE(P79,Q79) -> 45485
A80: CD-00079 | B80: CLI-0181 | C80: Lakeside Health | D80: Energy & Utilities | E80: LATAM | F80: Data & Analytics | G80: Existing Client Upsell | H80: REP-015 | I80: Yuki Garcia | J80: 45376 | K80: 45432 | L80: =K80-J80 -> 56 | M80: 91626.01 | N80: Lost | O80: No Decision/Timing
A81: CD-00080 | B81: CLI-0208 | C81: Continental Systems | D81: Retail & Consumer | E81: EMEA | F81: Risk & Compliance | G81: Inbound Marketing | H81: REP-022 | I81: Nikolai Sato | J81: 45392 | K81: 45434 | L81: =K81-J81 -> 42 | M81: 26015.9 | N81: Won | P81: 45452 | Q81: 4 | R81: =EDATE(P81,Q81) -> 45574
A82: CD-00081 | B82: CLI-0189 | C82: Cedar Materials | D82: Technology | E82: LATAM | F82: Risk & Compliance | G82: Partner Referral | H82: REP-020 | I82: Omar Lee | J82: 45349 | K82: 45435 | L82: =K82-J82 -> 86 | M82: 73317.26 | N82: Won | P82: 45444 | Q82: 4 | R82: =EDATE(P82,Q82) -> 45566
A83: CD-00082 | B83: CLI-0109 | C83: Sterling Dynamics | D83: Energy & Utilities | E83: LATAM | F83: Digital Transformation | G83: Event/Conference | H83: REP-015 | I83: Yuki Garcia | J83: 45379 | K83: 45440 | L83: =K83-J83 -> 61 | M83: 91946.24 | N83: Lost | O83: Budget Cut
A84: CD-00083 | B84: CLI-0172 | C84: Harbor Health | D84: Energy & Utilities | E84: LATAM | F84: Strategy Consulting | G84: Event/Conference | H84: REP-017 | I84: Tom Mansour | J84: 45364 | K84: 45441 | L84: =K84-J84 -> 77 | M84: 87374.89 | N84: Lost | O84: Went with In-house Team
A85: CD-00084 | B85: CLI-0034 | C85: Pioneer Technologies | D85: Manufacturing | E85: EMEA | F85: HR & Change Management | G85: Existing Client Upsell | H85: REP-012 | I85: Raj Chen | J85: 45383 | K85: 45445 | L85: =K85-J85 -> 62 | M85: 54965.88 | N85: Lost | O85: No Decision/Timing
A86: CD-00085 | B86: CLI-0230 | C86: Union Networks | D86: Healthcare | E86: LATAM | F86: Strategy Consulting | G86: RFP/Tender | H86: REP-007 | I86: Peter Khan | J86: 45386 | K86: 45447 | L86: =K86-J86 -> 61 | M86: 218947.65 | N86: Lost | O86: Price/Budget
A87: CD-00086 | B87: CLI-0059 | C87: Continental Bank | D87: Financial Services | E87: APAC | F87: Operations Consulting | G87: Existing Client Upsell | H87: REP-002 | I87: Aisha Sato | J87: 45371 | K87: 45452 | L87: =K87-J87 -> 81 | M87: 105532.52 | N87: Lost | O87: Scope Mismatch
A88: CD-00087 | B88: CLI-0189 | C88: Cedar Materials | D88: Technology | E88: LATAM | F88: Data & Analytics | G88: Event/Conference | H88: REP-020 | I88: Omar Lee | J88: 45404 | K88: 45452 | L88: =K88-J88 -> 48 | M88: 72563.55 | N88: Lost | O88: Lost to Competitor
A89: CD-00088 | B89: CLI-0248 | C89: Horizon Partners | D89: Energy & Utilities | E89: North America | F89: Risk & Compliance | G89: Inbound Marketing | H89: REP-007 | I89: Peter Khan | J89: 45297 | K89: 45453 | L89: =K89-J89 -> 156 | M89: 451429.08 | N89: Lost | O89: Scope Mismatch
A90: CD-00089 | B90: CLI-0180 | C90: Sterling Technologies | D90: Public Sector | E90: APAC | F90: Digital Transformation | G90: Event/Conference | H90: REP-006 | I90: Ahmed Müller | J90: 45400 | K90: 45453 | L90: =K90-J90 -> 53 | M90: 68927.05 | N90: Lost | O90: Price/Budget
A91: CD-00090 | B91: CLI-0086 | C91: Anchor Motors | D91: Healthcare | E91: LATAM | F91: Technology Consulting | G91: Outbound Prospecting | H91: REP-011 | I91: Aisha Kim | J91: 45356 | K91: 45453 | L91: =K91-J91 -> 97 | M91: 162751.17 | N91: Lost | O91: Scope Mismatch
A92: CD-00091 | B92: CLI-0103 | C92: Sterling Materials | D92: Financial Services | E92: North America | F92: HR & Change Management | G92: Outbound Prospecting | H92: REP-024 | I92: Lucas Mansour | J92: 45386 | K92: 45456 | L92: =K92-J92 -> 70 | M92: 94343.09 | N92: Won | P92: 45477 | Q92: 2 | R92: =EDATE(P92,Q92) -> 45539
A93: CD-00092 | B93: CLI-0229 | C93: Harbor Foods | D93: Manufacturing | E93: North America | F93: Financial Advisory | G93: Partner Referral | H93: REP-015 | I93: Yuki Garcia | J93: 45380 | K93: 45457 | L93: =K93-J93 -> 77 | M93: 101645.62 | N93: Lost | O93: Budget Cut
A94: CD-00093 | B94: CLI-0027 | C94: Crown Partners | D94: Manufacturing | E94: LATAM | F94: Strategy Consulting | G94: Partner Referral | H94: REP-024 | I94: Lucas Mansour | J94: 45375 | K94: 45458 | L94: =K94-J94 -> 83 | M94: 198522.27 | N94: Lost | O94: Price/Budget
A95: CD-00094 | B95: CLI-0257 | C95: North Foods | D95: Technology | E95: LATAM | F95: Risk & Compliance | G95: Partner Referral | H95: REP-006 | I95: Ahmed Müller | J95: 45434 | K95: 45464 | L95: =K95-J95 -> 30 | M95: 51701.04 | N95: Lost | O95: Scope Mismatch
A96: CD-00095 | B96: CLI-0061 | C96: Blue Solutions | D96: Telecom | E96: EMEA | F96: Data & Analytics | G96: Referral | H96: REP-008 | I96: Ingrid Johnson | J96: 45340 | K96: 45464 | L96: =K96-J96 -> 124 | M96: 311808.81 | N96: Lost | O96: Lost to Competitor
A97: CD-00096 | B97: CLI-0043 | C97: Pioneer Materials | D97: Technology | E97: EMEA | F97: Risk & Compliance | G97: Inbound Marketing | H97: REP-020 | I97: Omar Lee | J97: 45413 | K97: 45466 | L97: =K97-J97 -> 53 | M97: 79783.13 | N97: Lost | O97: Lost to Competitor
A98: CD-00097 | B98: CLI-0181 | C98: Lakeside Health | D98: Energy & Utilities | E98: LATAM | F98: Operations Consulting | G98: Inbound Marketing | H98: REP-010 | I98: Laura Sharma | J98: 45381 | K98: 45468 | L98: =K98-J98 -> 87 | M98: 120284.56 | N98: Lost | O98: Price/Budget
A99: CD-00098 | B99: CLI-0137 | C99: Meridian Capital | D99: Technology | E99: LATAM | F99: HR & Change Management | G99: Inbound Marketing | H99: REP-015 | I99: Yuki Garcia | J99: 45411 | K99: 45468 | L99: =K99-J99 -> 57 | M99: 70352.58 | N99: Won | P99: 45471 | Q99: 1 | R99: =EDATE(P99,Q99) -> 45501
A100: CD-00099 | B100: CLI-0185 | C100: Atlas Technologies | D100: Healthcare | E100: EMEA | F100: Risk & Compliance | G100: Event/Conference | H100: REP-022 | I100: Nikolai Sato | J100: 45337 | K100: 45468 | L100: =K100-J100 -> 131 | M100: 83786.36 | N100: Won | P100: 45491 | Q100: 3 | R100: =EDATE(P100,Q100) -> 45583
...

Sheet Open_Pipeline
A1: Opportunity_ID | B1: Client_ID | C1: Client_Name | D1: Industry | E1: Region | F1: Service_Line | G1: Lead_Source | H1: Sales_Rep_ID | I1: Sales_Rep_Name | J1: Created_Date | K1: Stage | L1: Stage_Probability | M1: Deal_Value_USD | N1: Weighted_Pipeline_Value | O1: Expected_Close_Date | P1: Age_In_Pipeline_Days | Q1: Days_To_Expected_Close
A2: OP-0001 | B2: CLI-0172 | C2: Harbor Health | D2: Energy & Utilities | E2: LATAM | F2: Strategy Consulting | G2: RFP/Tender | H2: REP-006 | I2: Ahmed Müller | J2: 45569 | K2: Prospecting | L2: 0.13 | M2: 259957.48 | N2: =L2*M2 -> 33794.472 | O2: 46493 | P2: =TODAY()-J2 -> 705 | Q2: =O2-TODAY() -> 219
A3: OP-0002 | B3: CLI-0232 | C3: Beacon Bank | D3: Healthcare | E3: EMEA | F3: Financial Advisory | G3: Event/Conference | H3: REP-023 | I3: Daniel Larsen | J3: 45639 | K3: Prospecting | L3: 0.19 | M3: 74493.54 | N3: =L3*M3 -> 14153.773 | O3: 46540 | P3: =TODAY()-J3 -> 635 | Q3: =O3-TODAY() -> 266
A4: OP-0003 | B4: CLI-0222 | C4: Cedar Dynamics | D4: Technology | E4: North America | F4: Risk & Compliance | G4: Referral | H4: REP-004 | I4: Wei Müller | J4: 45644 | K4: Qualification | L4: 0.25 | M4: 96626.08 | N4: =L4*M4 -> 24156.52 | O4: 46292 | P4: =TODAY()-J4 -> 630 | Q4: =O4-TODAY() -> 18
A5: OP-0004 | B5: CLI-0255 | C5: Bridgeway Telecom | D5: Energy & Utilities | E5: EMEA | F5: Technology Consulting | G5: Referral | H5: REP-013 | I5: Peter Costa | J5: 45650 | K5: Prospecting | L5: 0.07 | M5: 289784.37 | N5: =L5*M5 -> 20284.906 | O5: 46295 | P5: =TODAY()-J5 -> 624 | Q5: =O5-TODAY() -> 21
A6: OP-0005 | B6: CLI-0191 | C6: Beacon Energy | D6: Energy & Utilities | E6: LATAM | F6: Data & Analytics | G6: Existing Client Upsell | H6: REP-007 | I6: Peter Khan | J6: 45653 | K6: Qualification | L6: 0.21 | M6: 112138.61 | N6: =L6*M6 -> 23549.108 | O6: 46344 | P6: =TODAY()-J6 -> 621 | Q6: =O6-TODAY() -> 70
A7: OP-0006 | B7: CLI-0169 | C7: Continental Foods | D7: Technology | E7: APAC | F7: Financial Advisory | G7: Partner Referral | H7: REP-020 | I7: Omar Lee | J7: 45662 | K7: Prospecting | L7: 0.12 | M7: 132070.83 | N7: =L7*M7 -> 15848.5 | O7: 46542 | P7: =TODAY()-J7 -> 612 | Q7: =O7-TODAY() -> 268
A8: OP-0007 | B8: CLI-0148 | C8: Ironclad Dynamics | D8: Healthcare | E8: LATAM | F8: Technology Consulting | G8: Existing Client Upsell | H8: REP-003 | I8: Wei Brown | J8: 45670 | K8: Proposal/Solutioning | L8: 0.46 | M8: 140344.79 | N8: =L8*M8 -> 64558.603 | O8: 46517 | P8: =TODAY()-J8 -> 604 | Q8: =O8-TODAY() -> 243
A9: OP-0008 | B9: CLI-0260 | C9: Metro Group | D9: Manufacturing | E9: LATAM | F9: Financial Advisory | G9: Inbound Marketing | H9: REP-007 | I9: Peter Khan | J9: 45679 | K9: Prospecting | L9: 0.15 | M9: 49046.36 | N9: =L9*M9 -> 7356.954 | O9: 46485 | P9: =TODAY()-J9 -> 595 | Q9: =O9-TODAY() -> 211
A10: OP-0009 | B10: CLI-0018 | C10: Redwood Capital | D10: Energy & Utilities | E10: North America | F10: Operations Consulting | G10: Outbound Prospecting | H10: REP-015 | I10: Yuki Garcia | J10: 45691 | K10: Qualification | L10: 0.29 | M10: 75888.87 | N10: =L10*M10 -> 22007.772 | O10: 46452 | P10: =TODAY()-J10 -> 583 | Q10: =O10-TODAY() -> 178
A11: OP-0010 | B11: CLI-0247 | C11: Pioneer Retail | D11: Manufacturing | E11: North America | F11: HR & Change Management | G11: Existing Client Upsell | H11: REP-007 | I11: Peter Khan | J11: 45711 | K11: Negotiation | L11: 0.7 | M11: 46835.94 | N11: =L11*M11 -> 32785.158 | O11: 46515 | P11: =TODAY()-J11 -> 563 | Q11: =O11-TODAY() -> 241
A12: OP-0011 | B12: CLI-0197 | C12: Falcon Solutions | D12: Financial Services | E12: EMEA | F12: Data & Analytics | G12: Partner Referral | H12: REP-024 | I12: Lucas Mansour | J12: 45712 | K12: Qualification | L12: 0.23 | M12: 115112.67 | N12: =L12*M12 -> 26475.914 | O12: 46461 | P12: =TODAY()-J12 -> 562 | Q12: =O12-TODAY() -> 187
A13: OP-0012 | B13: CLI-0191 | C13: Beacon Energy | D13: Energy & Utilities | E13: LATAM | F13: Data & Analytics | G13: Existing Client Upsell | H13: REP-015 | I13: Yuki Garcia | J13: 45725 | K13: Prospecting | L13: 0.1 | M13: 149250.34 | N13: =L13*M13 -> 14925.034 | O13: 46501 | P13: =TODAY()-J13 -> 549 | Q13: =O13-TODAY() -> 227
... A151: OP-0150 | B151: CLI-0012 | C151: Coastal Enterprises | D151: Telecom | E151: North America | F151: Strategy Consulting | G151: Inbound Marketing | H151: REP-022 | I151: Nikolai Sato | J151: 46270 | K151: Prospecting | L151: 0.13 | M151: 171672.4 | N151: =L151*M151 -> 22317.412 | O151: 46361 | P151: =TODAY()-J151 -> 4 | Q151: =O151-TODAY() -> 87

Sheet Clients
A1: Client_ID | B1: Client_Name | C1: Industry | D1: Region | E1: Total_Closed_Opportunities | F1: Deals_Won | G1: Deals_Lost | H1: Win_Rate | I1: Total_Revenue_Won | J1: Avg_Deal_Size_Won | K1: First_Project_End_Date | L1: Last_Project_End_Date | M1: Open_Pipeline_Count | N1: Open_Pipeline_Value | O1: Days_Since_Last_Project | P1: Repeat_Client | Q1: Client_Status
A2: CLI-0001 | B2: Falcon Industries | C2: Energy & Utilities | D2: EMEA | E2: =COUNTIF(Closed_Deals!$B$2:$B$761,A2) -> 0 | F2: =COUNTIFS(Closed_Deals!$B$2:$B$761,A2,Closed_Deals!$N$2:$N$761,"Won") -> 0 | G2: =E2-F2 -> 0 | H2: =IFERROR(F2/E2,"") | I2: =SUMIFS(Closed_Deals!$M$2:$M$761,Closed_Deals!$B$2:$B$761,A2,Closed_Deals!$N$2:$N$761,"Won") -> 0 | J2: =IFERROR(I2/F2,"") | K2: =IF(F2=0,"",_xlfn.MINIFS(Closed_Deals!$R$2:$R$761,Closed_Deals!$B$2:$B$761,A2,Closed_Deals!$N$2:$N$761,"Won")) | L2: =IF(F2=0,"",_xlfn.MAXIFS(Closed_Deals!$R$2:$R$761,Closed_Deals!$B$2:$B$761,A2,Closed_Deals!$N$2:$N$761,"Won")) | M2: =COUNTIF(Open_Pipeline!$B$2:$B$151,A2) -> 1 | N2: =SUMIF(Open_Pipeline!$B$2:$B$151,A2,Open_Pipeline!$M$2:$M$151) -> 166090.92 | O2: =IF(F2=0,"",TODAY()-L2) | P2: =IF(F2>=2,"Yes","No") -> No | Q2: =IF(F2=0,"No Won Business",IF(M2>0,"Active - In Pipeline",IF(O2<=365,"Active",IF(O2<=545,"At Risk","Churned")))) -> No Won Business
A3: CLI-0002 | B3: Crown Retail | C3: Telecom | D3: EMEA | E3: =COUNTIF(Closed_Deals!$B$2:$B$761,A3) -> 2 | F3: =COUNTIFS(Closed_Deals!$B$2:$B$761,A3,Closed_Deals!$N$2:$N$761,"Won") -> 0 | G3: =E3-F3 -> 2 | H3: =IFERROR(F3/E3,"") -> 0 | I3: =SUMIFS(Closed_Deals!$M$2:$M$761,Closed_Deals!$B$2:$B$761,A3,Closed_Deals!$N$2:$N$761,"Won") -> 0 | J3: =IFERROR(I3/F3,"") | K3: =IF(F3=0,"",_xlfn.MINIFS(Closed_Deals!$R$2:$R$761,Closed_Deals!$B$2:$B$761,A3,Closed_Deals!$N$2:$N$761,"Won")) | L3: =IF(F3=0,"",_xlfn.MAXIFS(Closed_Deals!$R$2:$R$761,Closed_Deals!$B$2:$B$761,A3,Closed_Deals!$N$2:$N$761,"Won")) | M3: =COUNTIF(Open_Pipeline!$B$2:$B$151,A3) -> 0 | N3: =SUMIF(Open_Pipeline!$B$2:$B$151,A3,Open_Pipeline!$M$2:$M$151) -> 0 | O3: =IF(F3=0,"",TODAY()-L3) | P3: =IF(F3>=2,"Yes","No") -> No | Q3: =IF(F3=0,"No Won Business",IF(M3>0,"Active - In Pipeline",IF(O3<=365,"Active",IF(O3<=545,"At Risk","Churned")))) -> No Won Business
A4: CLI-0003 | B4: Ironclad Energy | C4: Financial Services | D4: EMEA | E4: =COUNTIF(Closed_Deals!$B$2:$B$761,A4) -> 5 | F4: =COUNTIFS(Closed_Deals!$B$2:$B$761,A4,Closed_Deals!$N$2:$N$761,"Won") -> 2 | G4: =E4-F4 -> 3 | H4: =IFERROR(F4/E4,"") -> 0.4 | I4: =SUMIFS(Closed_Deals!$M$2:$M$761,Closed_Deals!$B$2:$B$761,A4,Closed_Deals!$N$2:$N$761,"Won") -> 186176.95 | J4: =IFERROR(I4/F4,"") -> 93088.475 | K4: =IF(F4=0,"",_xlfn.MINIFS(Closed_Deals!$R$2:$R$761,Closed_Deals!$B$2:$B$761,A4,Closed_Deals!$N$2:$N$761,"Won")) -> 45943 | L4: =IF(F4=0,"",_xlfn.MAXIFS(Closed_Deals!$R$2:$R$761,Closed_Deals!$B$2:$B$761,A4,Closed_Deals!$N$2:$N$761,"Won")) -> 46241 | M4: =COUNTIF(Open_Pipeline!$B$2:$B$151,A4) -> 0 | N4: =SUMIF(Open_Pipeline!$B$2:$B$151,A4,Open_Pipeline!$M$2:$M$151) -> 0 | O4: =IF(F4=0,"",TODAY()-L4) -> 33 | P4: =IF(F4>=2,"Yes","No") -> Yes | Q4: =IF(F4=0,"No Won Business",IF(M4>0,"Active - In Pipeline",IF(O4<=365,"Active",IF(O4<=545,"At Risk","Churned")))) -> Active
A5: CLI-0004 | B5: Falcon Bank | C5: Public Sector | D5: EMEA | E5: =COUNTIF(Closed_Deals!$B$2:$B$761,A5) -> 0 | F5: =COUNTIFS(Closed_Deals!$B$2:$B$761,A5,Closed_Deals!$N$2:$N$761,"Won") -> 0 | G5: =E5-F5 -> 0 | H5: =IFERROR(F5/E5,"") | I5: =SUMIFS(Closed_Deals!$M$2:$M$761,Closed_Deals!$B$2:$B$761,A5,Closed_Deals!$N$2:$N$761,"Won") -> 0 | J5: =IFERROR(I5/F5,"") | K5: =IF(F5=0,"",_xlfn.MINIFS(Closed_Deals!$R$2:$R$761,Closed_Deals!$B$2:$B$761,A5,Closed_Deals!$N$2:$N$761,"Won")) | L5: =IF(F5=0,"",_xlfn.MAXIFS(Closed_Deals!$R$2:$R$761,Closed_Deals!$B$2:$B$761,A5,Closed_Deals!$N$2:$N$761,"Won")) | M5: =COUNTIF(Open_Pipeline!$B$2:$B$151,A5) -> 0 | N5: =SUMIF(Open_Pipeline!$B$2:$B$151,A5,Open_Pipeline!$M$2:$M$151) -> 0 | O5: =IF(F5=0,"",TODAY()-L5) | P5: =IF(F5>=2,"Yes","No") -> No | Q5: =IF(F5=0,"No Won Business",IF(M5>0,"Active - In Pipeline",IF(O5<=365,"Active",IF(O5<=545,"At Risk","Churned")))) -> No Won Business
A6: CLI-0005 | B6: Horizon Retail | C6: Energy & Utilities | D6: North America | E6: =COUNTIF(Closed_Deals!$B$2:$B$761,A6) -> 0 | F6: =COUNTIFS(Closed_Deals!$B$2:$B$761,A6,Closed_Deals!$N$2:$N$761,"Won") -> 0 | G6: =E6-F6 -> 0 | H6: =IFERROR(F6/E6,"") | I6: =SUMIFS(Closed_Deals!$M$2:$M$761,Closed_Deals!$B$2:$B$761,A6,Closed_Deals!$N$2:$N$761,"Won") -> 0 | J6: =IFERROR(I6/F6,"") | K6: =IF(F6=0,"",_xlfn.MINIFS(Closed_Deals!$R$2:$R$761,Closed_Deals!$B$2:$B$761,A6,Closed_Deals!$N$2:$N$761,"Won")) | L6: =IF(F6=0,"",_xlfn.MAXIFS(Closed_Deals!$R$2:$R$761,Closed_Deals!$B$2:$B$761,A6,Closed_Deals!$N$2:$N$761,"Won")) | M6: =COUNTIF(Open_Pipeline!$B$2:$B$151,A6) -> 0 | N6: =SUMIF(Open_Pipeline!$B$2:$B$151,A6,Open_Pipeline!$M$2:$M$151) -> 0 | O6: =IF(F6=0,"",TODAY()-L6) | P6: =IF(F6>=2,"Yes","No") -> No | Q6: =IF(F6=0,"No Won Business",IF(M6>0,"Active - In Pipeline",IF(O6<=365,"Active",IF(O6<=545,"At Risk","Churned")))) -> No Won Business
A7: CLI-0006 | B7: Anchor Holdings | C7: Public Sector | D7: LATAM | E7: =COUNTIF(Closed_Deals!$B$2:$B$761,A7) -> 3 | F7: =COUNTIFS(Closed_Deals!$B$2:$B$761,A7,Closed_Deals!$N$2:$N$761,"Won") -> 0 | G7: =E7-F7 -> 3 | H7: =IFERROR(F7/E7,"") -> 0 | I7: =SUMIFS(Closed_Deals!$M$2:$M$761,Closed_Deals!$B$2:$B$761,A7,Closed_Deals!$N$2:$N$761,"Won") -> 0 | J7: =IFERROR(I7/F7,"") | K7: =IF(F7=0,"",_xlfn.MINIFS(Closed_Deals!$R$2:$R$761,Closed_Deals!$B$2:$B$761,A7,Closed_Deals!$N$2:$N$761,"Won")) | L7: =IF(F7=0,"",_xlfn.MAXIFS(Closed_Deals!$R$2:$R$761,Closed_Deals!$B$2:$B$761,A7,Closed_Deals!$N$2:$N$761,"Won")) | M7: =COUNTIF(Open_Pipeline!$B$2:$B$151,A7) -> 1 | N7: =SUMIF(Open_Pipeline!$B$2:$B$151,A7,Open_Pipeline!$M$2:$M$151) -> 83111.47 | O7: =IF(F7=0,"",TODAY()-L7) | P7: =IF(F7>=2,"Yes","No") -> No | Q7: =IF(F7=0,"No Won Business",IF(M7>0,"Active - In Pipeline",IF(O7<=365,"Active",IF(O7<=545,"At Risk","Churned")))) -> No Won Business
A8: CLI-0007 | B8: Orion Energy | C8: Retail & Consumer | D8: LATAM | E8: =COUNTIF(Closed_Deals!$B$2:$B$761,A8) -> 3 | F8: =COUNTIFS(Closed_Deals!$B$2:$B$761,A8,Closed_Deals!$N$2:$N$761,"Won") -> 2 | G8: =E8-F8 -> 1 | H8: =IFERROR(F8/E8,"") -> 0.66666667 | I8: =SUMIFS(Closed_Deals!$M$2:$M$761,Closed_Deals!$B$2:$B$761,A8,Closed_Deals!$N$2:$N$761,"Won") -> 228422.28 | J8: =IFERROR(I8/F8,"") -> 114211.14 | K8: =IF(F8=0,"",_xlfn.MINIFS(Closed_Deals!$R$2:$R$761,Closed_Deals!$B$2:$B$761,A8,Closed_Deals!$N$2:$N$761,"Won")) -> 45958 | L8: =IF(F8=0,"",_xlfn.MAXIFS(Closed_Deals!$R$2:$R$761,Closed_Deals!$B$2:$B$761,A8,Closed_Deals!$N$2:$N$761,"Won")) -> 46305 | M8: =COUNTIF(Open_Pipeline!$B$2:$B$151,A8) -> 0 | N8: =SUMIF(Open_Pipeline!$B$2:$B$151,A8,Open_Pipeline!$M$2:$M$151) -> 0 | O8: =IF(F8=0,"",TODAY()-L8) -> -31 | P8: =IF(F8>=2,"Yes","No") -> Yes | Q8: =IF(F8=0,"No Won Business",IF(M8>0,"Active - In Pipeline",IF(O8<=365,"Active",IF(O8<=545,"At Risk","Churned")))) -> Active
A9: CLI-0008 | B9: Harbor Materials | C9: Financial Services | D9: North America | E9: =COUNTIF(Closed_Deals!$B$2:$B$761,A9) -> 0 | F9: =COUNTIFS(Closed_Deals!$B$2:$B$761,A9,Closed_Deals!$N$2:$N$761,"Won") -> 0 | G9: =E9-F9 -> 0 | H9: =IFERROR(F9/E9,"") | I9: =SUMIFS(Closed_Deals!$M$2:$M$761,Closed_Deals!$B$2:$B$761,A9,Closed_Deals!$N$2:$N$761,"Won") -> 0 | J9: =IFERROR(I9/F9,"") | K9: =IF(F9=0,"",_xlfn.MINIFS(Closed_Deals!$R$2:$R$761,Closed_Deals!$B$2:$B$761,A9,Closed_Deals!$N$2:$N$761,"Won")) | L9: =IF(F9=0,"",_xlfn.MAXIFS(Closed_Deals!$R$2:$R$761,Closed_Deals!$B$2:$B$761,A9,Closed_Deals!$N$2:$N$761,"Won")) | M9: =COUNTIF(Open_Pipeline!$B$2:$B$151,A9) -> 0 | N9: =SUMIF(Open_Pipeline!$B$2:$B$151,A9,Open_Pipeline!$M$2:$M$151) -> 0 | O9: =IF(F9=0,"",TODAY()-L9) | P9: =IF(F9>=2,"Yes","No") -> No | Q9: =IF(F9=0,"No Won Business",IF(M9>0,"Active - In Pipeline",IF(O9<=365,"Active",IF(O9<=545,"At Risk","Churned")))) -> No Won Business
A10: CLI-0009 | B10: Falcon Retail | C10: Energy & Utilities | D10: EMEA | E10: =COUNTIF(Closed_Deals!$B$2:$B$761,A10) -> 4 | F10: =COUNTIFS(Closed_Deals!$B$2:$B$761,A10,Closed_Deals!$N$2:$N$761,"Won") -> 1 | G10: =E10-F10 -> 3 | H10: =IFERROR(F10/E10,"") -> 0.25 | I10: =SUMIFS(Closed_Deals!$M$2:$M$761,Closed_Deals!$B$2:$B$761,A10,Closed_Deals!$N$2:$N$761,"Won") -> 190533.37 | J10: =IFERROR(I10/F10,"") -> 190533.37 | K10: =IF(F10=0,"",_xlfn.MINIFS(Closed_Deals!$R$2:$R$761,Closed_Deals!$B$2:$B$761,A10,Closed_Deals!$N$2:$N$761,"Won")) -> 45764 | L10: =IF(F10=0,"",_xlfn.MAXIFS(Closed_Deals!$R$2:$R$761,Closed_Deals!$B$2:$B$761,A10,Closed_Deals!$N$2:$N$761,"Won")) -> 45764 | M10: =COUNTIF(Open_Pipeline!$B$2:$B$151,A10) -> 1 | N10: =SUMIF(Open_Pipeline!$B$2:$B$151,A10,Open_Pipeline!$M$2:$M$151) -> 134914.55 | O10: =IF(F10=0,"",TODAY()-L10) -> 510 | P10: =IF(F10>=2,"Yes","No") -> No | Q10: =IF(F10=0,"No Won Business",IF(M10>0,"Active - In Pipeline",IF(O10<=365,"Active",IF(O10<=545,"At Risk","Churned")))) -> Active - In Pipeline
A11: CLI-0010 | B11: Blue Health | C11: Technology | D11: APAC | E11: =COUNTIF(Closed_Deals!$B$2:$B$761,A11) -> 6 | F11: =COUNTIFS(Closed_Deals!$B$2:$B$761,A11,Closed_Deals!$N$2:$N$761,"Won") -> 3 | G11: =E11-F11 -> 3 | H11: =IFERROR(F11/E11,"") -> 0.5 | I11: =SUMIFS(Closed_Deals!$M$2:$M$761,Closed_Deals!$B$2:$B$761,A11,Closed_Deals!$N$2:$N$761,"Won") -> 243602.8 | J11: =IFERROR(I11/F11,"") -> 81200.933 | K11: =IF(F11=0,"",_xlfn.MINIFS(Closed_Deals!$R$2:$R$761,Closed_Deals!$B$2:$B$761,A11,Closed_Deals!$N$2:$N$761,"Won")) -> 45870 | L11: =IF(F11=0,"",_xlfn.MAXIFS(Closed_Deals!$R$2:$R$761,Closed_Deals!$B$2:$B$761,A11,Closed_Deals!$N$2:$N$761,"Won")) -> 46033 | M11: =COUNTIF(Open_Pipeline!$B$2:$B$151,A11) -> 0 | N11: =SUMIF(Open_Pipeline!$B$2:$B$151,A11,Open_Pipeline!$M$2:$M$151) -> 0 | O11: =IF(F11=0,"",TODAY()-L11) -> 241 | P11: =IF(F11>=2,"Yes","No") -> Yes | Q11: =IF(F11=0,"No Won Business",IF(M11>0,"Active - In Pipeline",IF(O11<=365,"Active",IF(O11<=545,"At Risk","Churned")))) -> Active
A12: CLI-0011 | B12: Blue Materials | C12: Public Sector | D12: EMEA | E12: =COUNTIF(Closed_Deals!$B$2:$B$761,A12) -> 0 | F12: =COUNTIFS(Closed_Deals!$B$2:$B$761,A12,Closed_Deals!$N$2:$N$761,"Won") -> 0 | G12: =E12-F12 -> 0 | H12: =IFERROR(F12/E12,"") | I12: =SUMIFS(Closed_Deals!$M$2:$M$761,Closed_Deals!$B$2:$B$761,A12,Closed_Deals!$N$2:$N$761,"Won") -> 0 | J12: =IFERROR(I12/F12,"") | K12: =IF(F12=0,"",_xlfn.MINIFS(Closed_Deals!$R$2:$R$761,Closed_Deals!$B$2:$B$761,A12,Closed_Deals!$N$2:$N$761,"Won")) | L12: =IF(F12=0,"",_xlfn.MAXIFS(Closed_Deals!$R$2:$R$761,Closed_Deals!$B$2:$B$761,A12,Closed_Deals!$N$2:$N$761,"Won")) | M12: =COUNTIF(Open_Pipeline!$B$2:$B$151,A12) -> 0 | N12: =SUMIF(Open_Pipeline!$B$2:$B$151,A12,Open_Pipeline!$M$2:$M$151) -> 0 | O12: =IF(F12=0,"",TODAY()-L12) | P12: =IF(F12>=2,"Yes","No") -> No | Q12: =IF(F12=0,"No Won Business",IF(M12>0,"Active - In Pipeline",IF(O12<=365,"Active",IF(O12<=545,"At Risk","Churned")))) -> No Won Business
A13: CLI-0012 | B13: Coastal Enterprises | C13: Telecom | D13: North America | E13: =COUNTIF(Closed_Deals!$B$2:$B$761,A13) -> 5 | F13: =COUNTIFS(Closed_Deals!$B$2:$B$761,A13,Closed_Deals!$N$2:$N$761,"Won") -> 3 | G13: =E13-F13 -> 2 | H13: =IFERROR(F13/E13,"") -> 0.6 | I13: =SUMIFS(Closed_Deals!$M$2:$M$761,Closed_Deals!$B$2:$B$761,A13,Closed_Deals!$N$2:$N$761,"Won") -> 231140.61 | J13: =IFERROR(I13/F13,"") -> 77046.87 | K13: =IF(F13=0,"",_xlfn.MINIFS(Closed_Deals!$R$2:$R$761,Closed_Deals!$B$2:$B$761,A13,Closed_Deals!$N$2:$N$761,"Won")) -> 45877 | L13: =IF(F13=0,"",_xlfn.MAXIFS(Closed_Deals!$R$2:$R$761,Closed_Deals!$B$2:$B$761,A13,Closed_Deals!$N$2:$N$761,"Won")) -> 46060 | M13: =COUNTIF(Open_Pipeline!$B$2:$B$151,A13) -> 2 | N13: =SUMIF(Open_Pipeline!$B$2:$B$151,A13,Open_Pipeline!$M$2:$M$151) -> 318732.42 | O13: =IF(F13=0,"",TODAY()-L13) -> 214 | P13: =IF(F13>=2,"Yes","No") -> Yes | Q13: =IF(F13=0,"No Won Business",IF(M13>0,"Active - In Pipeline",IF(O13<=365,"Active",IF(O13<=545,"At Risk","Churned")))) -> Active - In Pipeline
... A261: CLI-0260 | B261: Metro Group | C261: Manufacturing | D261: LATAM | E261: =COUNTIF(Closed_Deals!$B$2:$B$761,A261) -> 3 | F261: =COUNTIFS(Closed_Deals!$B$2:$B$761,A261,Closed_Deals!$N$2:$N$761,"Won") -> 2 | G261: =E261-F261 -> 1 | H261: =IFERROR(F261/E261,"") -> 0.66666667 | I261: =SUMIFS(Closed_Deals!$M$2:$M$761,Closed_Deals!$B$2:$B$761,A261,Closed_Deals!$N$2:$N$761,"Won") -> 139649.1 | J261: =IFERROR(I261/F261,"") -> 69824.55 | K261: =IF(F261=0,"",_xlfn.MINIFS(Closed_Deals!$R$2:$R$761,Closed_Deals!$B$2:$B$761,A261,Closed_Deals!$N$2:$N$761,"Won")) -> 45591 | L261: =IF(F261=0,"",_xlfn.MAXIFS(Closed_Deals!$R$2:$R$761,Closed_Deals!$B$2:$B$761,A261,Closed_Deals!$N$2:$N$761,"Won")) -> 45834 | M261: =COUNTIF(Open_Pipeline!$B$2:$B$151,A261) -> 3 | N261: =SUMIF(Open_Pipeline!$B$2:$B$151,A261,Open_Pipeline!$M$2:$M$151) -> 175199.93 | O261: =IF(F261=0,"",TODAY()-L261) -> 440 | P261: =IF(F261>=2,"Yes","No") -> Yes | Q261: =IF(F261=0,"No Won Business",IF(M261>0,"Active - In Pipeline",IF(O261<=365,"Active",IF(O261<=545,"At Risk","Churned")))) -> Active - In Pipeline

Sheet Sales_Reps
A1: Rep_ID | B1: Rep_Name | C1: Region | D1: Hire_Date | E1: Total_Deals_Closed | F1: Deals_Won | G1: Win_Rate | H1: Total_Revenue_Won | I1: Avg_Sales_Cycle_Days_Won | J1: Open_Pipeline_Count | K1: Open_Pipeline_Value
A2: REP-001 | B2: Wei Mansour | C2: North America | D2: 45052 | E2: =COUNTIF(Closed_Deals!$H$2:$H$761,A2) -> 43 | F2: =COUNTIFS(Closed_Deals!$H$2:$H$761,A2,Closed_Deals!$N$2:$N$761,"Won") -> 12 | G2: =IFERROR(F2/E2,"") -> 0.27906977 | H2: =SUMIFS(Closed_Deals!$M$2:$M$761,Closed_Deals!$H$2:$H$761,A2,Closed_Deals!$N$2:$N$761,"Won") -> 1464172.3 | I2: =IFERROR(AVERAGEIFS(Closed_Deals!$L$2:$L$761,Closed_Deals!$H$2:$H$761,A2,Closed_Deals!$N$2:$N$761,"Won"),"") -> 78.583333 | J2: =COUNTIF(Open_Pipeline!$H$2:$H$151,A2) -> 5 | K2: =SUMIF(Open_Pipeline!$H$2:$H$151,A2,Open_Pipeline!$M$2:$M$151) -> 721771.77
A3: REP-002 | B3: Aisha Sato | C3: EMEA | D3: 45660 | E3: =COUNTIF(Closed_Deals!$H$2:$H$761,A3) -> 31 | F3: =COUNTIFS(Closed_Deals!$H$2:$H$761,A3,Closed_Deals!$N$2:$N$761,"Won") -> 12 | G3: =IFERROR(F3/E3,"") -> 0.38709677 | H3: =SUMIFS(Closed_Deals!$M$2:$M$761,Closed_Deals!$H$2:$H$761,A3,Closed_Deals!$N$2:$N$761,"Won") -> 1344950 | I3: =IFERROR(AVERAGEIFS(Closed_Deals!$L$2:$L$761,Closed_Deals!$H$2:$H$761,A3,Closed_Deals!$N$2:$N$761,"Won"),"") -> 80.5 | J3: =COUNTIF(Open_Pipeline!$H$2:$H$151,A3) -> 11 | K3: =SUMIF(Open_Pipeline!$H$2:$H$151,A3,Open_Pipeline!$M$2:$M$151) -> 1394813.4
A4: REP-003 | B4: Wei Brown | C4: APAC | D4: 43701 | E4: =COUNTIF(Closed_Deals!$H$2:$H$761,A4) -> 35 | F4: =COUNTIFS(Closed_Deals!$H$2:$H$761,A4,Closed_Deals!$N$2:$N$761,"Won") -> 11 | G4: =IFERROR(F4/E4,"") -> 0.31428571 | H4: =SUMIFS(Closed_Deals!$M$2:$M$761,Closed_Deals!$H$2:$H$761,A4,Closed_Deals!$N$2:$N$761,"Won") -> 1240621.9 | I4: =IFERROR(AVERAGEIFS(Closed_Deals!$L$2:$L$761,Closed_Deals!$H$2:$H$761,A4,Closed_Deals!$N$2:$N$761,"Won"),"") -> 83.636364 | J4: =COUNTIF(Open_Pipeline!$H$2:$H$151,A4) -> 9 | K4: =SUMIF(Open_Pipeline!$H$2:$H$151,A4,Open_Pipeline!$M$2:$M$151) -> 751698.31
A5: REP-004 | B5: Wei Müller | C5: LATAM | D5: 46009 | E5: =COUNTIF(Closed_Deals!$H$2:$H$761,A5) -> 18 | F5: =COUNTIFS(Closed_Deals!$H$2:$H$761,A5,Closed_Deals!$N$2:$N$761,"Won") -> 8 | G5: =IFERROR(F5/E5,"") -> 0.44444444 | H5: =SUMIFS(Closed_Deals!$M$2:$M$761,Closed_Deals!$H$2:$H$761,A5,Closed_Deals!$N$2:$N$761,"Won") -> 912807.47 | I5: =IFERROR(AVERAGEIFS(Closed_Deals!$L$2:$L$761,Closed_Deals!$H$2:$H$761,A5,Closed_Deals!$N$2:$N$761,"Won"),"") -> 83.125 | J5: =COUNTIF(Open_Pipeline!$H$2:$H$151,A5) -> 6 | K5: =SUMIF(Open_Pipeline!$H$2:$H$151,A5,Open_Pipeline!$M$2:$M$151) -> 758026.98
A6: REP-005 | B6: Grace Lee | C6: North America | D6: 45239 | E6: =COUNTIF(Closed_Deals!$H$2:$H$761,A6) -> 30 | F6: =COUNTIFS(Closed_Deals!$H$2:$H$761,A6,Closed_Deals!$N$2:$N$761,"Won") -> 8 | G6: =IFERROR(F6/E6,"") -> 0.26666667 | H6: =SUMIFS(Closed_Deals!$M$2:$M$761,Closed_Deals!$H$2:$H$761,A6,Closed_Deals!$N$2:$N$761,"Won") -> 870559.52 | I6: =IFERROR(AVERAGEIFS(Closed_Deals!$L$2:$L$761,Closed_Deals!$H$2:$H$761,A6,Closed_Deals!$N$2:$N$761,"Won"),"") -> 83.375 | J6: =COUNTIF(Open_Pipeline!$H$2:$H$151,A6) -> 4 | K6: =SUMIF(Open_Pipeline!$H$2:$H$151,A6,Open_Pipeline!$M$2:$M$151) -> 250978.33
A7: REP-006 | B7: Ahmed Müller | C7: EMEA | D7: 43482 | E7: =COUNTIF(Closed_Deals!$H$2:$H$761,A7) -> 27 | F7: =COUNTIFS(Closed_Deals!$H$2:$H$761,A7,Closed_Deals!$N$2:$N$761,"Won") -> 9 | G7: =IFERROR(F7/E7,"") -> 0.33333333 | H7: =SUMIFS(Closed_Deals!$M$2:$M$761,Closed_Deals!$H$2:$H$761,A7,Closed_Deals!$N$2:$N$761,"Won") -> 920988.18 | I7: =IFERROR(AVERAGEIFS(Closed_Deals!$L$2:$L$761,Closed_Deals!$H$2:$H$761,A7,Closed_Deals!$N$2:$N$761,"Won"),"") -> 75.444444 | J7: =COUNTIF(Open_Pipeline!$H$2:$H$151,A7) -> 4 | K7: =SUMIF(Open_Pipeline!$H$2:$H$151,A7,Open_Pipeline!$M$2:$M$151) -> 581785.88
A8: REP-007 | B8: Peter Khan | C8: APAC | D8: 44592 | E8: =COUNTIF(Closed_Deals!$H$2:$H$761,A8) -> 35 | F8: =COUNTIFS(Closed_Deals!$H$2:$H$761,A8,Closed_Deals!$N$2:$N$761,"Won") -> 6 | G8: =IFERROR(F8/E8,"") -> 0.17142857 | H8: =SUMIFS(Closed_Deals!$M$2:$M$761,Closed_Deals!$H$2:$H$761,A8,Closed_Deals!$N$2:$N$761,"Won") -> 511928.52 | I8: =IFERROR(AVERAGEIFS(Closed_Deals!$L$2:$L$761,Closed_Deals!$H$2:$H$761,A8,Closed_Deals!$N$2:$N$761,"Won"),"") -> 76.666667 | J8: =COUNTIF(Open_Pipeline!$H$2:$H$151,A8) -> 9 | K8: =SUMIF(Open_Pipeline!$H$2:$H$151,A8,Open_Pipeline!$M$2:$M$151) -> 760151.13
A9: REP-008 | B9: Ingrid Johnson | C9: LATAM | D9: 45863 | E9: =COUNTIF(Closed_Deals!$H$2:$H$761,A9) -> 38 | F9: =COUNTIFS(Closed_Deals!$H$2:$H$761,A9,Closed_Deals!$N$2:$N$761,"Won") -> 15 | G9: =IFERROR(F9/E9,"") -> 0.39473684 | H9: =SUMIFS(Closed_Deals!$M$2:$M$761,Closed_Deals!$H$2:$H$761,A9,Closed_Deals!$N$2:$N$761,"Won") -> 1796390.7 | I9: =IFERROR(AVERAGEIFS(Closed_Deals!$L$2:$L$761,Closed_Deals!$H$2:$H$761,A9,Closed_Deals!$N$2:$N$761,"Won"),"") -> 80.133333 | J9: =COUNTIF(Open_Pipeline!$H$2:$H$151,A9) -> 3 | K9: =SUMIF(Open_Pipeline!$H$2:$H$151,A9,Open_Pipeline!$M$2:$M$151) -> 492023.33
A10: REP-009 | B10: Ahmed Petrov | C10: North America | D10: 44300 | E10: =COUNTIF(Closed_Deals!$H$2:$H$761,A10) -> 30 | F10: =COUNTIFS(Closed_Deals!$H$2:$H$761,A10,Closed_Deals!$N$2:$N$761,"Won") -> 9 | G10: =IFERROR(F10/E10,"") -> 0.3 | H10: =SUMIFS(Closed_Deals!$M$2:$M$761,Closed_Deals!$H$2:$H$761,A10,Closed_Deals!$N$2:$N$761,"Won") -> 1075090.8 | I10: =IFERROR(AVERAGEIFS(Closed_Deals!$L$2:$L$761,Closed_Deals!$H$2:$H$761,A10,Closed_Deals!$N$2:$N$761,"Won"),"") -> 86.444444 | J10: =COUNTIF(Open_Pipeline!$H$2:$H$151,A10) -> 8 | K10: =SUMIF(Open_Pipeline!$H$2:$H$151,A10,Open_Pipeline!$M$2:$M$151) -> 1497383.4
A11: REP-010 | B11: Laura Sharma | C11: EMEA | D11: 44422 | E11: =COUNTIF(Closed_Deals!$H$2:$H$761,A11) -> 32 | F11: =COUNTIFS(Closed_Deals!$H$2:$H$761,A11,Closed_Deals!$N$2:$N$761,"Won") -> 10 | G11: =IFERROR(F11/E11,"") -> 0.3125 | H11: =SUMIFS(Closed_Deals!$M$2:$M$761,Closed_Deals!$H$2:$H$761,A11,Closed_Deals!$N$2:$N$761,"Won") -> 567713.5 | I11: =IFERROR(AVERAGEIFS(Closed_Deals!$L$2:$L$761,Closed_Deals!$H$2:$H$761,A11,Closed_Deals!$N$2:$N$761,"Won"),"") -> 66.4 | J11: =COUNTIF(Open_Pipeline!$H$2:$H$151,A11) -> 4 | K11: =SUMIF(Open_Pipeline!$H$2:$H$151,A11,Open_Pipeline!$M$2:$M$151) -> 407936.12
A12: REP-011 | B12: Aisha Kim | C12: APAC | D12: 43375 | E12: =COUNTIF(Closed_Deals!$H$2:$H$761,A12) -> 33 | F12: =COUNTIFS(Closed_Deals!$H$2:$H$761,A12,Closed_Deals!$N$2:$N$761,"Won") -> 9 | G12: =IFERROR(F12/E12,"") -> 0.27272727 | H12: =SUMIFS(Closed_Deals!$M$2:$M$761,Closed_Deals!$H$2:$H$761,A12,Closed_Deals!$N$2:$N$761,"Won") -> 1510405.9 | I12: =IFERROR(AVERAGEIFS(Closed_Deals!$L$2:$L$761,Closed_Deals!$H$2:$H$761,A12,Closed_Deals!$N$2:$N$761,"Won"),"") -> 87.111111 | J12: =COUNTIF(Open_Pipeline!$H$2:$H$151,A12) -> 11 | K12: =SUMIF(Open_Pipeline!$H$2:$H$151,A12,Open_Pipeline!$M$2:$M$151) -> 1203982.7
A13: REP-012 | B13: Raj Chen | C13: LATAM | D13: 43291 | E13: =COUNTIF(Closed_Deals!$H$2:$H$761,A13) -> 25 | F13: =COUNTIFS(Closed_Deals!$H$2:$H$761,A13,Closed_Deals!$N$2:$N$761,"Won") -> 9 | G13: =IFERROR(F13/E13,"") -> 0.36 | H13: =SUMIFS(Closed_Deals!$M$2:$M$761,Closed_Deals!$H$2:$H$761,A13,Closed_Deals!$N$2:$N$761,"Won") -> 1020233.8 | I13: =IFERROR(AVERAGEIFS(Closed_Deals!$L$2:$L$761,Closed_Deals!$H$2:$H$761,A13,Closed_Deals!$N$2:$N$761,"Won"),"") -> 67.888889 | J13: =COUNTIF(Open_Pipeline!$H$2:$H$151,A13) -> 4 | K13: =SUMIF(Open_Pipeline!$H$2:$H$151,A13,Open_Pipeline!$M$2:$M$151) -> 347477.99
... A25: REP-024 | B25: Lucas Mansour | C25: LATAM | D25: 43665 | E25: =COUNTIF(Closed_Deals!$H$2:$H$761,A25) -> 37 | F25: =COUNTIFS(Closed_Deals!$H$2:$H$761,A25,Closed_Deals!$N$2:$N$761,"Won") -> 10 | G25: =IFERROR(F25/E25,"") -> 0.27027027 | H25: =SUMIFS(Closed_Deals!$M$2:$M$761,Closed_Deals!$H$2:$H$761,A25,Closed_Deals!$N$2:$N$761,"Won") -> 1215913.2 | I25: =IFERROR(AVERAGEIFS(Closed_Deals!$L$2:$L$761,Closed_Deals!$H$2:$H$761,A25,Closed_Deals!$N$2:$N$761,"Won"),"") -> 78.5 | J25: =COUNTIF(Open_Pipeline!$H$2:$H$151,A25) -> 6 | K25: =SUMIF(Open_Pipeline!$H$2:$H$151,A25,Open_Pipeline!$M$2:$M$151) -> 515462.27

Sheet KPI_Summary
A1: Meridian Consulting Group — Sales & Pipeline KPI Summary
A2: All figures below are formulas referencing Closed_Deals, Open_Pipeline, and Clients — recalculates automatically.
A4: Headline KPIs
A5: Total Historical Opportunities (3yr) | B5: =COUNTA(Closed_Deals!$A$2:$A$761) -> 760
A6: Total Won | B6: =COUNTIF(Closed_Deals!$N$2:$N$761,"Won") -> 246
A7: Total Lost | B7: =COUNTIF(Closed_Deals!$N$2:$N$761,"Lost") -> 514
A8: Overall Win % | B8: =B6/B5 -> 0.32368421
A9: Total Revenue Won (3yr) | B9: =SUMIF(Closed_Deals!$N$2:$N$761,"Won",Closed_Deals!$M$2:$M$761) -> 27351415
A10: Avg Deal Size — Won | B10: =AVERAGEIF(Closed_Deals!$N$2:$N$761,"Won",Closed_Deals!$M$2:$M$761) -> 111184.61
A11: Avg Deal Size — Lost | B11: =AVERAGEIF(Closed_Deals!$N$2:$N$761,"Lost",Closed_Deals!$M$2:$M$761) -> 112791.28
A12: Avg Sales Cycle Days — Won | B12: =AVERAGEIFS(Closed_Deals!$L$2:$L$761,Closed_Deals!$N$2:$N$761,"Won") -> 78.634146
A13: Avg Sales Cycle Days — Lost | B13: =AVERAGEIFS(Closed_Deals!$L$2:$L$761,Closed_Deals!$N$2:$N$761,"Lost") -> 77.153696
A14: Total Open Pipeline Opportunities | B14: =COUNTA(Open_Pipeline!$A$2:$A$151) -> 150
A15: Total Open Pipeline Value | B15: =SUM(Open_Pipeline!$M$2:$M$151) -> 16406754
A16: Weighted Open Pipeline Value | B16: =SUM(Open_Pipeline!$N$2:$N$151) -> 4812140.1
A17: Total Clients | B17: =COUNTA(Clients!$A$2:$A$261) -> 260
A18: Clients With Won Business | B18: =COUNTIFS(Clients!$F$2:$F$261,">0") -> 126
A19: Repeat Clients (2+ Won Deals) | B19: =COUNTIF(Clients!$P$2:$P$261,"Yes") -> 62
A20: Repeat Client Rate (of clients w/ won business) | B20: =B19/B18 -> 0.49206349
A21: Active Clients | B21: =COUNTIF(Clients!$Q$2:$Q$261,"Active")+COUNTIF(Clients!$Q$2:$Q$261,"Active - In Pipeline") -> 108
A22: At-Risk Clients | B22: =COUNTIF(Clients!$Q$2:$Q$261,"At Risk") -> 9
A23: Churned Clients | B23: =COUNTIF(Clients!$Q$2:$Q$261,"Churned") -> 9
A24: Churn Rate (of clients w/ won business) | B24: =B23/(B21+B22+B23) -> 0.071428571
A26: Win % by Service Line
A27: Service_Line | B27: Total | C27: Won | D27: Lost | E27: Win_Rate | F27: Revenue_Won
A28: Data & Analytics | B28: =COUNTIF(Closed_Deals!$F$2:$F$761,$A28) -> 85 | C28: =COUNTIFS(Closed_Deals!$F$2:$F$761,$A28,Closed_Deals!$N$2:$N$761,"Won") -> 32 | D28: =B28-C28 -> 53 | E28: =IFERROR(C28/B28,"") -> 0.37647059 | F28: =SUMIFS(Closed_Deals!$M$2:$M$761,Closed_Deals!$F$2:$F$761,$A28,Closed_Deals!$N$2:$N$761,"Won") -> 3754159.6
A29: Digital Transformation | B29: =COUNTIF(Closed_Deals!$F$2:$F$761,$A29) -> 102 | C29: =COUNTIFS(Closed_Deals!$F$2:$F$761,$A29,Closed_Deals!$N$2:$N$761,"Won") -> 26 | D29: =B29-C29 -> 76 | E29: =IFERROR(C29/B29,"") -> 0.25490196 | F29: =SUMIFS(Closed_Deals!$M$2:$M$761,Closed_Deals!$F$2:$F$761,$A29,Closed_Deals!$N$2:$N$761,"Won") -> 4159440.4
A30: Financial Advisory | B30: =COUNTIF(Closed_Deals!$F$2:$F$761,$A30) -> 90 | C30: =COUNTIFS(Closed_Deals!$F$2:$F$761,$A30,Closed_Deals!$N$2:$N$761,"Won") -> 31 | D30: =B30-C30 -> 59 | E30: =IFERROR(C30/B30,"") -> 0.34444444 | F30: =SUMIFS(Closed_Deals!$M$2:$M$761,Closed_Deals!$F$2:$F$761,$A30,Closed_Deals!$N$2:$N$761,"Won") -> 3737095.8
A31: HR & Change Management | B31: =COUNTIF(Closed_Deals!$F$2:$F$761,$A31) -> 98 | C31: =COUNTIFS(Closed_Deals!$F$2:$F$761,$A31,Closed_Deals!$N$2:$N$761,"Won") -> 38 | D31: =B31-C31 -> 60 | E31: =IFERROR(C31/B31,"") -> 0.3877551 | F31: =SUMIFS(Closed_Deals!$M$2:$M$761,Closed_Deals!$F$2:$F$761,$A31,Closed_Deals!$N$2:$N$761,"Won") -> 3119217.4
A32: Operations Consulting | B32: =COUNTIF(Closed_Deals!$F$2:$F$761,$A32) -> 99 | C32: =COUNTIFS(Closed_Deals!$F$2:$F$761,$A32,Closed_Deals!$N$2:$N$761,"Won") -> 31 | D32: =B32-C32 -> 68 | E32: =IFERROR(C32/B32,"") -> 0.31313131 | F32: =SUMIFS(Closed_Deals!$M$2:$M$761,Closed_Deals!$F$2:$F$761,$A32,Closed_Deals!$N$2:$N$761,"Won") -> 2916992.7
A33: Risk & Compliance | B33: =COUNTIF(Closed_Deals!$F$2:$F$761,$A33) -> 91 | C33: =COUNTIFS(Closed_Deals!$F$2:$F$761,$A33,Closed_Deals!$N$2:$N$761,"Won") -> 28 | D33: =B33-C33 -> 63 | E33: =IFERROR(C33/B33,"") -> 0.30769231 | F33: =SUMIFS(Closed_Deals!$M$2:$M$761,Closed_Deals!$F$2:$F$761,$A33,Closed_Deals!$N$2:$N$761,"Won") -> 2153158.5
A34: Strategy Consulting | B34: =COUNTIF(Closed_Deals!$F$2:$F$761,$A34) -> 95 | C34: =COUNTIFS(Closed_Deals!$F$2:$F$761,$A34,Closed_Deals!$N$2:$N$761,"Won") -> 26 | D34: =B34-C34 -> 69 | E34: =IFERROR(C34/B34,"") -> 0.27368421 | F34: =SUMIFS(Closed_Deals!$M$2:$M$761,Closed_Deals!$F$2:$F$761,$A34,Closed_Deals!$N$2:$N$761,"Won") -> 3232040.4
A35: Technology Consulting | B35: =COUNTIF(Closed_Deals!$F$2:$F$761,$A35) -> 100 | C35: =COUNTIFS(Closed_Deals!$F$2:$F$761,$A35,Closed_Deals!$N$2:$N$761,"Won") -> 34 | D35: =B35-C35 -> 66 | E35: =IFERROR(C35/B35,"") -> 0.34 | F35: =SUMIFS(Closed_Deals!$M$2:$M$761,Closed_Deals!$F$2:$F$761,$A35,Closed_Deals!$N$2:$N$761,"Won") -> 4279309.8
A37: Win % by Region
A38: Region | B38: Total | C38: Won | D38: Lost | E38: Win_Rate | F38: Revenue_Won
A39: North America | B39: =COUNTIF(Closed_Deals!$E$2:$E$761,$A39) -> 212 | C39: =COUNTIFS(Closed_Deals!$E$2:$E$761,$A39,Closed_Deals!$N$2:$N$761,"Won") -> 79 | D39: =B39-C39 -> 133 | E39: =IFERROR(C39/B39,"") -> 0.37264151 | F39: =SUMIFS(Closed_Deals!$M$2:$M$761,Closed_Deals!$E$2:$E$761,$A39,Closed_Deals!$N$2:$N$761,"Won") -> 9252360.3
A40: EMEA | B40: =COUNTIF(Closed_Deals!$E$2:$E$761,$A40) -> 136 | C40: =COUNTIFS(Closed_Deals!$E$2:$E$761,$A40,Closed_Deals!$N$2:$N$761,"Won") -> 38 | D40: =B40-C40 -> 98 | E40: =IFERROR(C40/B40,"") -> 0.27941176 | F40: =SUMIFS(Closed_Deals!$M$2:$M$761,Closed_Deals!$E$2:$E$761,$A40,Closed_Deals!$N$2:$N$761,"Won") -> 3900392.2
A41: APAC | B41: =COUNTIF(Closed_Deals!$E$2:$E$761,$A41) -> 165 | C41: =COUNTIFS(Closed_Deals!$E$2:$E$761,$A41,Closed_Deals!$N$2:$N$761,"Won") -> 55 | D41: =B41-C41 -> 110 | E41: =IFERROR(C41/B41,"") -> 0.33333333 | F41: =SUMIFS(Closed_Deals!$M$2:$M$761,Closed_Deals!$E$2:$E$761,$A41,Closed_Deals!$N$2:$N$761,"Won") -> 6111510.4
A42: LATAM | B42: =COUNTIF(Closed_Deals!$E$2:$E$761,$A42) -> 247 | C42: =COUNTIFS(Closed_Deals!$E$2:$E$761,$A42,Closed_Deals!$N$2:$N$761,"Won") -> 74 | D42: =B42-C42 -> 173 | E42: =IFERROR(C42/B42,"") -> 0.29959514 | F42: =SUMIFS(Closed_Deals!$M$2:$M$761,Closed_Deals!$E$2:$E$761,$A42,Closed_Deals!$N$2:$N$761,"Won") -> 8087151.5
A44: Win % by Lead Source
A45: Lead_Source | B45: Total | C45: Won | D45: Lost | E45: Win_Rate | F45: Revenue_Won
A46: Event/Conference | B46: =COUNTIF(Closed_Deals!$G$2:$G$761,$A46) -> 102 | C46: =COUNTIFS(Closed_Deals!$G$2:$G$761,$A46,Closed_Deals!$N$2:$N$761,"Won") -> 33 | D46: =B46-C46 -> 69 | E46: =IFERROR(C46/B46,"") -> 0.32352941 | F46: =SUMIFS(Closed_Deals!$M$2:$M$761,Closed_Deals!$G$2:$G$761,$A46,Closed_Deals!$N$2:$N$761,"Won") -> 3961660.9
A47: Existing Client Upsell | B47: =COUNTIF(Closed_Deals!$G$2:$G$761,$A47) -> 107 | C47: =COUNTIFS(Closed_Deals!$G$2:$G$761,$A47,Closed_Deals!$N$2:$N$761,"Won") -> 41 | D47: =B47-C47 -> 66 | E47: =IFERROR(C47/B47,"") -> 0.38317757 | F47: =SUMIFS(Closed_Deals!$M$2:$M$761,Closed_Deals!$G$2:$G$761,$A47,Closed_Deals!$N$2:$N$761,"Won") -> 4534718.2
A48: Inbound Marketing | B48: =COUNTIF(Closed_Deals!$G$2:$G$761,$A48) -> 105 | C48: =COUNTIFS(Closed_Deals!$G$2:$G$761,$A48,Closed_Deals!$N$2:$N$761,"Won") -> 38 | D48: =B48-C48 -> 67 | E48: =IFERROR(C48/B48,"") -> 0.36190476 | F48: =SUMIFS(Closed_Deals!$M$2:$M$761,Closed_Deals!$G$2:$G$761,$A48,Closed_Deals!$N$2:$N$761,"Won") -> 4128241.5
A49: Outbound Prospecting | B49: =COUNTIF(Closed_Deals!$G$2:$G$761,$A49) -> 118 | C49: =COUNTIFS(Closed_Deals!$G$2:$G$761,$A49,Closed_Deals!$N$2:$N$761,"Won") -> 41 | D49: =B49-C49 -> 77 | E49: =IFERROR(C49/B49,"") -> 0.34745763 | F49: =SUMIFS(Closed_Deals!$M$2:$M$761,Closed_Deals!$G$2:$G$761,$A49,Closed_Deals!$N$2:$N$761,"Won") -> 4584991.1
A50: Partner Referral | B50: =COUNTIF(Closed_Deals!$G$2:$G$761,$A50) -> 113 | C50: =COUNTIFS(Closed_Deals!$G$2:$G$761,$A50,Closed_Deals!$N$2:$N$761,"Won") -> 33 | D50: =B50-C50 -> 80 | E50: =IFERROR(C50/B50,"") -> 0.2920354 | F50: =SUMIFS(Closed_Deals!$M$2:$M$761,Closed_Deals!$G$2:$G$761,$A50,Closed_Deals!$N$2:$N$761,"Won") -> 3326945.3
A51: RFP/Tender | B51: =COUNTIF(Closed_Deals!$G$2:$G$761,$A51) -> 118 | C51: =COUNTIFS(Closed_Deals!$G$2:$G$761,$A51,Closed_Deals!$N$2:$N$761,"Won") -> 33 | D51: =B51-C51 -> 85 | E51: =IFERROR(C51/B51,"") -> 0.27966102 | F51: =SUMIFS(Closed_Deals!$M$2:$M$761,Closed_Deals!$G$2:$G$761,$A51,Closed_Deals!$N$2:$N$761,"Won") -> 3993811.3
A52: Referral | B52: =COUNTIF(Closed_Deals!$G$2:$G$761,$A52) -> 97 | C52: =COUNTIFS(Closed_Deals!$G$2:$G$761,$A52,Closed_Deals!$N$2:$N$761,"Won") -> 27 | D52: =B52-C52 -> 70 | E52: =IFERROR(C52/B52,"") -> 0.27835052 | F52: =SUMIFS(Closed_Deals!$M$2:$M$761,Closed_Deals!$G$2:$G$761,$A52,Closed_Deals!$N$2:$N$761,"Won") -> 2821046.2
A54: Open Pipeline by Stage
A55: Stage | B55: Count | C55: Total_Value | D55: Weighted_Value | E55: Avg_Probability
A56: Prospecting | B56: =COUNTIF(Open_Pipeline!$K$2:$K$151,$A56) -> 55 | C56: =SUMIF(Open_Pipeline!$K$2:$K$151,$A56,Open_Pipeline!$M$2:$M$151) -> 6536497.8 | D56: =SUMIF(Open_Pipeline!$K$2:$K$151,$A56,Open_Pipeline!$N$2:$N$151) -> 689368.54 | E56: =IFERROR(AVERAGEIF(Open_Pipeline!$K$2:$K$151,$A56,Open_Pipeline!$L$2:$L$151),"") -> 0.10218182
A57: Qualification | B57: =COUNTIF(Open_Pipeline!$K$2:$K$151,$A57) -> 46 | C57: =SUMIF(Open_Pipeline!$K$2:$K$151,$A57,Open_Pipeline!$M$2:$M$151) -> 5007992 | D57: =SUMIF(Open_Pipeline!$K$2:$K$151,$A57,Open_Pipeline!$N$2:$N$151) -> 1303572 | E57: =IFERROR(AVERAGEIF(Open_Pipeline!$K$2:$K$151,$A57,Open_Pipeline!$L$2:$L$151),"") -> 0.25478261
A58: Proposal/Solutioning | B58: =COUNTIF(Open_Pipeline!$K$2:$K$151,$A58) -> 33 | C58: =SUMIF(Open_Pipeline!$K$2:$K$151,$A58,Open_Pipeline!$M$2:$M$151) -> 3167666.9 | D58: =SUMIF(Open_Pipeline!$K$2:$K$151,$A58,Open_Pipeline!$N$2:$N$151) -> 1536657.4 | E58: =IFERROR(AVERAGEIF(Open_Pipeline!$K$2:$K$151,$A58,Open_Pipeline!$L$2:$L$151),"") -> 0.48818182
A59: Negotiation | B59: =COUNTIF(Open_Pipeline!$K$2:$K$151,$A59) -> 16 | C59: =SUMIF(Open_Pipeline!$K$2:$K$151,$A59,Open_Pipeline!$M$2:$M$151) -> 1694597.2 | D59: =SUMIF(Open_Pipeline!$K$2:$K$151,$A59,Open_Pipeline!$N$2:$N$151) -> 1282542.1 | E59: =IFERROR(AVERAGEIF(Open_Pipeline!$K$2:$K$151,$A59,Open_Pipeline!$L$2:$L$151),"") -> 0.749375
A61: Lost Deals by Loss Reason
A62: Loss_Reason | B62: Count | C62: % of All Lost Deals
A63: Budget Cut | B63: =COUNTIF(Closed_Deals!$O$2:$O$761,$A63) -> 77 | C63: =IFERROR(B63/$B$7,"") -> 0.14980545
A64: Lost to Competitor | B64: =COUNTIF(Closed_Deals!$O$2:$O$761,$A64) -> 81 | C64: =IFERROR(B64/$B$7,"") -> 0.15758755
A65: No Decision/Timing | B65: =COUNTIF(Closed_Deals!$O$2:$O$761,$A65) -> 101 | C65: =IFERROR(B65/$B$7,"") -> 0.19649805
A66: Price/Budget | B66: =COUNTIF(Closed_Deals!$O$2:$O$761,$A66) -> 88 | C66: =IFERROR(B66/$B$7,"") -> 0.17120623
A67: Scope Mismatch | B67: =COUNTIF(Closed_Deals!$O$2:$O$761,$A67) -> 83 | C67: =IFERROR(B67/$B$7,"") -> 0.1614786
A68: Went with In-house Team | B68: =COUNTIF(Closed_Deals!$O$2:$O$761,$A68) -> 84 | C68: =IFERROR(B68/$B$7,"") -> 0.16342412
A70: Client Status Breakdown
A71: Client_Status | B71: Count | C71: % of Total Clients
A72: No Won Business | B72: =COUNTIF(Clients!$Q$2:$Q$261,$A72) -> 134 | C72: =IFERROR(B72/$B$17,"") -> 0.51538462
A73: Active | B73: =COUNTIF(Clients!$Q$2:$Q$261,$A73) -> 41 | C73: =IFERROR(B73/$B$17,"") -> 0.15769231
A74: Active - In Pipeline | B74: =COUNTIF(Clients!$Q$2:$Q$261,$A74) -> 67 | C74: =IFERROR(B74/$B$17,"") -> 0.25769231
A75: At Risk | B75: =COUNTIF(Clients!$Q$2:$Q$261,$A75) -> 9 | C75: =IFERROR(B75/$B$17,"") -> 0.034615385
A76: Churned | B76: =COUNTIF(Clients!$Q$2:$Q$261,$A76) -> 9 | C76: =IFERROR(B76/$B$17,"") -> 0.034615385
